<mbm>
  <entry id="0">
    <source>{f859}{0300}その依頼は、魔法で魔物狩りを{f801}生業にしている人からの依頼なの。{f801}{f802}狩りの方法は特殊で、見えないように{f801}魔法陣の罠を仕掛けて、それを踏んだ魔物を{f801}どかんと吹き飛ばすやり方なんですって。{f801}{f802}だけど、魔法陣の罠を仕掛けた後日の今、{f801}依頼人本人がケガをしちゃって、{f801}動けないらしいのよ。{f801}{f802}だから、あなたたちには罠を仕掛けた{f804}{0500}5階{f804}{0000}に{f801}行ってもらって、仕掛けた罠の解除を{f801}お願いしたいの。{f801}{f802}場所はこの辺りだって言ってたわ。{f801}</source>
    <target>{f859}{0300}その依頼は、魔法で魔物狩りを{f801}生業にしている人からの依頼なの。{f801}{f802}狩りの方法は特殊で、見えないように{f801}魔法陣の罠を仕掛けて、それを踏んだ魔物を{f801}どかんと吹き飛ばすやり方なんですって。{f801}{f802}だけど、魔法陣の罠を仕掛けた後日の今、{f801}依頼人本人がケガをしちゃって、{f801}動けないらしいのよ。{f801}{f802}だから、あなたたちには罠を仕掛けた{f804}{0500}5階{f804}{0000}に{f801}行ってもらって、仕掛けた罠の解除を{f801}お願いしたいの。{f801}{f802}場所はこの辺りだって言ってたわ。{f801}</target>
  </entry>
  <entry id="1">
    <source>{f804}{0300}新たな目的地が表示されました!{f804}{0000}{f801}</source>
    <target>{f804}{0300}新たな目的地が表示されました!{f804}{0000}{f801}</target>
  </entry>
  <entry id="2">
    <source>{f859}{0300}じゃあ次は、その罠を探すために{f801}必要なアイテムを渡しておくわね。{f801}</source>
    <target>{f859}{0300}じゃあ次は、その罠を探すために{f801}必要なアイテムを渡しておくわね。{f801}</target>
  </entry>
  <entry id="3">
    <source>{f859}{0300}今渡した魔力検知機は近くにある魔法陣の{f801}反応を検知できるから、それを上手く使えば{f801}罠を見つけられる、だそうよ。{f801}{f802}ただ問題があって、その魔力検知機、{f801}検知の精度はいまいちみたいなのよ。{f801}{f802}地図上で{f804}{0500}自分が立っている場所を中心にして{f801}隣の1マスにいくつ反応があるのか{f801}その数を光{f804}{0000}で教えてくれるんですって。{f801}{f802}自分の周囲に2つ罠があっても、{f801}{f804}{0500}その2つが東西南北のどこにあるかまでは{f801}分からない{f804}{0000}ってことね。{f801}{f802}どう? 今ので魔力検知機の使い方は{f801}理解できたかしら?{f801}</source>
    <target>{f859}{0300}今渡した魔力検知機は近くにある魔法陣の{f801}反応を検知できるから、それを上手く使えば{f801}罠を見つけられる、だそうよ。{f801}{f802}ただ問題があって、その魔力検知機、{f801}検知の精度はいまいちみたいなのよ。{f801}{f802}地図上で{f804}{0500}自分が立っている場所を中心にして{f801}隣の1マスにいくつ反応があるのか{f801}その数を光{f804}{0000}で教えてくれるんですって。{f801}{f802}自分の周囲に2つ罠があっても、{f801}{f804}{0500}その2つが東西南北のどこにあるかまでは{f801}分からない{f804}{0000}ってことね。{f801}{f802}どう? 今ので魔力検知機の使い方は{f801}理解できたかしら?{f801}</target>
  </entry>
  <entry id="4">
    <source>{f804}{0500}何と答えますか?{f804}{0000}{f801}理解できた{f801}もう一度教えてほしい{f801}</source>
    <target>{f804}{0500}何と答えますか?{f804}{0000}{f801}理解できた{f801}もう一度教えてほしい{f801}</target>
  </entry>
  <entry id="5">
    <source>{f859}{0300}{f81b}{565f}{4348}{4152}{5f31}{3032}{2f42}{4154}{544c}{452f}{534b}{5f44}{4546}{2f30}{3032}{0000}うんうん、それならよかったわ。{f801}それじゃ、次に罠を解除するための{f801}アイテムを渡すわね。{f801}</source>
    <target>{f859}{0300}{f81b}{565f}{4348}{4152}{5f31}{3032}{2f42}{4154}{544c}{452f}{534b}{5f44}{4546}{2f30}{3032}{0000}うんうん、それならよかったわ。{f801}それじゃ、次に罠を解除するための{f801}アイテムを渡すわね。{f801}</target>
  </entry>
  <entry id="6">
    <source>{f859}{0300}それを地面に貼れば、魔法陣の魔力をお札が{f801}吸い取って、魔法陣は消滅するそうよ。{f801}{f802}そして仕掛けられた{f804}{0500}罠の数は3つ{f804}{0000}。{f801}あなたたちが使える{f804}{0500}お札は5つ{f804}{0000}。{f801}{f802}{f804}{0500}使うべきところを間違ったら、{f801}足りなくなる{f804}{0000}から気を付けるのよ?{f801}{f802}そうね、もし不安なら{f804}{0500}魔力を感知する力{f804}{0000}を{f801}持った人をパーティに入れるといいかもね。{f801}{f802}{f81b}{565f}{4348}{4152}{5f31}{3032}{2f53}{5953}{5445}{4d2f}{4d45}{4e55}{2f69}{6e66}{6f00}{0000}さ、それじゃあ頑張ってきてちょうだいね?{f801}</source>
    <target>{f859}{0300}それを地面に貼れば、魔法陣の魔力をお札が{f801}吸い取って、魔法陣は消滅するそうよ。{f801}{f802}そして仕掛けられた{f804}{0500}罠の数は3つ{f804}{0000}。{f801}あなたたちが使える{f804}{0500}お札は5つ{f804}{0000}。{f801}{f802}{f804}{0500}使うべきところを間違ったら、{f801}足りなくなる{f804}{0000}から気を付けるのよ?{f801}{f802}そうね、もし不安なら{f804}{0500}魔力を感知する力{f804}{0000}を{f801}持った人をパーティに入れるといいかもね。{f801}{f802}{f81b}{565f}{4348}{4152}{5f31}{3032}{2f53}{5953}{5445}{4d2f}{4d45}{4e55}{2f69}{6e66}{6f00}{0000}さ、それじゃあ頑張ってきてちょうだいね?{f801}</target>
  </entry>
  <entry id="7">
    <source>{f859}{0300}了解よ。ちゃんと覚えてからじゃないと{f801}危ないもの。それじゃもう一回{f801}説明させてもらうわね?{f801}</source>
    <target>{f859}{0300}了解よ。ちゃんと覚えてからじゃないと{f801}危ないもの。それじゃもう一回{f801}説明させてもらうわね?{f801}</target>
  </entry>
  <entry id="15">
    <source>{f859}{0300}魔物狩りから受けた依頼が終わったの?{f801}おつかれさま。{f801}{f802}その様子だと何の問題もなく、{f801}達成してきたみたいね。{f801}やるじゃない、あなたたち。{f801}{f802}さて、それじゃあなたたちには{f801}今回の働きに対するご褒美を{f801}渡さなくちゃね。{f801}{f802}{f81b}{565f}{4348}{4152}{5f31}{3032}{2f42}{4154}{544c}{452f}{5649}{4354}{4f52}{592f}{6561}{7379}{0000}はい、これが今回の働きに対する報酬よ。{f801}またお願いね。{f801}</source>
    <target>{f859}{0300}魔物狩りから受けた依頼が終わったの?{f801}おつかれさま。{f801}{f802}その様子だと何の問題もなく、{f801}達成してきたみたいね。{f801}やるじゃない、あなたたち。{f801}{f802}さて、それじゃあなたたちには{f801}今回の働きに対するご褒美を{f801}渡さなくちゃね。{f801}{f802}{f81b}{565f}{4348}{4152}{5f31}{3032}{2f42}{4154}{544c}{452f}{5649}{4354}{4f52}{592f}{6561}{7379}{0000}はい、これが今回の働きに対する報酬よ。{f801}またお願いね。{f801}</target>
  </entry>
  <entry id="16">
    <source>{f859}{0300}魔物狩りから受けた依頼が終わったの?{f801}おつかれさま。{f801}{f802}あら、ちょっと服がこげちゃってるわね。{f801}もしかして罠にかかっちゃったの?{f801}{f802}じゃあ、報酬を渡すから、{f801}今日は早めに休んだ方がいいわ。{f801}{f802}{f81b}{565f}{4348}{4152}{5f31}{3032}{2f45}{5645}{4e54}{2f47}{454e}{4552}{414c}{2f30}{3132}{0000}はい、これが今回の働きに対する報酬よ。{f801}またお願いね。{f801}</source>
    <target>{f859}{0300}魔物狩りから受けた依頼が終わったの?{f801}おつかれさま。{f801}{f802}あら、ちょっと服がこげちゃってるわね。{f801}もしかして罠にかかっちゃったの?{f801}{f802}じゃあ、報酬を渡すから、{f801}今日は早めに休んだ方がいいわ。{f801}{f802}{f81b}{565f}{4348}{4152}{5f31}{3032}{2f45}{5645}{4e54}{2f47}{454e}{4552}{414c}{2f30}{3132}{0000}はい、これが今回の働きに対する報酬よ。{f801}またお願いね。{f801}</target>
  </entry>
  <entry id="17">
    <source>{f859}{0300}魔物狩りから受けた依頼が終わったの?{f801}おつかれさま。{f801}{f802}って、体中ボロボロじゃない!{f801}大丈夫なの!?{f801}{f802}まあ、帰って来られたから{f801}そこまで大きな問題はないのかもだけど…。{f801}{f802}{f81b}{565f}{4348}{4152}{5f31}{3032}{2f45}{5645}{4e54}{2f47}{454e}{4552}{414c}{2f30}{3033}{0000}うーん…、今回の依頼は{f801}ちょっと難題だったのかしら…。{f801}{f802}あ、待たせちゃってごめんなさいね。{f801}これが今回の報酬よ。{f801}</source>
    <target>{f859}{0300}魔物狩りから受けた依頼が終わったの?{f801}おつかれさま。{f801}{f802}って、体中ボロボロじゃない!{f801}大丈夫なの!?{f801}{f802}まあ、帰って来られたから{f801}そこまで大きな問題はないのかもだけど…。{f801}{f802}{f81b}{565f}{4348}{4152}{5f31}{3032}{2f45}{5645}{4e54}{2f47}{454e}{4552}{414c}{2f30}{3033}{0000}うーん…、今回の依頼は{f801}ちょっと難題だったのかしら…。{f801}{f802}あ、待たせちゃってごめんなさいね。{f801}これが今回の報酬よ。{f801}</target>
  </entry>
  <entry id="20">
    <source>君たちは酒場で受けた依頼の指定に従い、{f801}罠として設置された魔法陣のある部屋に{f801}たどり着いた。{f801}{f802}依頼人のいっていたことが真実なら{f801}罠は踏んでしまうと爆発してしまうはずだ。{f801}{f802}君たちはそうならないように預けられた{f801}魔力検知機を使って、罠のある場所を{f801}探し当てなくてはならない。{f801}{f802}また君たちの中に魔力を感知する能力に{f801}長けたものがいるならば、その力を{f801}頼ってもいいだろう。{f801}</source>
    <target>君たちは酒場で受けた依頼の指定に従い、{f801}罠として設置された魔法陣のある部屋に{f801}たどり着いた。{f801}{f802}依頼人のいっていたことが真実なら{f801}罠は踏んでしまうと爆発してしまうはずだ。{f801}{f802}君たちはそうならないように預けられた{f801}魔力検知機を使って、罠のある場所を{f801}探し当てなくてはならない。{f801}{f802}また君たちの中に魔力を感知する能力に{f801}長けたものがいるならば、その力を{f801}頼ってもいいだろう。{f801}</target>
  </entry>
  <entry id="25">
    <source>仕掛けられていた罠を踏んだ君たちは{f801}手痛いダメージを受けることとなった。{f801}{f802}だが、これで魔法陣の罠は{f801}一つ解除できたともいえる。{f801}</source>
    <target>仕掛けられていた罠を踏んだ君たちは{f801}手痛いダメージを受けることとなった。{f801}{f802}だが、これで魔法陣の罠は{f801}一つ解除できたともいえる。{f801}</target>
  </entry>
  <entry id="26">
    <source>その事実を受け止めながら、{f801}君たちは未だ残る罠を解除するために{f801}再び行動を開始してもいい。{f801}</source>
    <target>その事実を受け止めながら、{f801}君たちは未だ残る罠を解除するために{f801}再び行動を開始してもいい。{f801}</target>
  </entry>
  <entry id="27">
    <source>そして君たちは、今解除したものが{f801}罠の3つ目だったことに気付く。{f801}{f802}君たちは無事に依頼を達成したのだ!{f801}後は時間のある時に酒場へ行き、{f801}このことを報告するといいだろう。{f801}</source>
    <target>そして君たちは、今解除したものが{f801}罠の3つ目だったことに気付く。{f801}{f802}君たちは無事に依頼を達成したのだ!{f801}後は時間のある時に酒場へ行き、{f801}このことを報告するといいだろう。{f801}</target>
  </entry>
  <entry id="30">
    <source>{f804}{0500}どうしますか?{f804}{0000}{f801}魔力検知機を使う{f801}魔力感知できる者の力を頼る{f801}罠を解除する{f801}何もしないでおく{f801}</source>
    <target>{f804}{0500}どうしますか?{f804}{0000}{f801}魔力検知機を使う{f801}魔力感知できる者の力を頼る{f801}罠を解除する{f801}何もしないでおく{f801}</target>
  </entry>
  <entry id="35">
    <source>君たちは魔力検知機を取り出し、{f801}使用してみる…。{f801}{f802}すると、魔力検知機の内部が{f801}カチャカチャと音を立て始める。{f801}{f802}やがてカチャカチャという音は止まり、{f801}代わりに小気味いいチーンッという音が{f801}部屋の中に鳴り響く。{f801}{f802}どうやら検知が終了したようだ。{f801}君たちはどれどれと、いくつ反応が{f801}返ってきたか確認してみる…。{f801}{f802}だが、いくつ反応があったかを示すランプに{f801}灯った光はない。どうやら君たちの周囲には{f801}罠はないようだ…。{f801}</source>
    <target>君たちは魔力検知機を取り出し、{f801}使用してみる…。{f801}{f802}すると、魔力検知機の内部が{f801}カチャカチャと音を立て始める。{f801}{f802}やがてカチャカチャという音は止まり、{f801}代わりに小気味いいチーンッという音が{f801}部屋の中に鳴り響く。{f801}{f802}どうやら検知が終了したようだ。{f801}君たちはどれどれと、いくつ反応が{f801}返ってきたか確認してみる…。{f801}{f802}だが、いくつ反応があったかを示すランプに{f801}灯った光はない。どうやら君たちの周囲には{f801}罠はないようだ…。{f801}</target>
  </entry>
  <entry id="36">
    <source>君たちは魔力検知機を取り出し、{f801}使用してみる…。{f801}{f802}すると、魔力検知機の内部が{f801}カチャカチャと音を立て始める。{f801}{f802}やがてカチャカチャという音は止まり、{f801}代わりに小気味いいチーンッという音が{f801}部屋の中に鳴り響く。{f801}{f802}どうやら検知が終了したようだ。{f801}君たちはどれどれと、いくつ反応が{f801}返ってきたか確認してみる…。{f801}{f802}反応を示すランプには光が{f804}{0500}{f810}{0000}つ{f804}{0000}{f801}灯っている!{f801}{f802}どうやら今の君たちの周りには{f804}{0500}{f810}{0000}つ{f804}{0000}の{f801}罠が埋まっているようだ。{f801}{f802}君たちは今得た情報を元に{f801}次の行動に出る必要がある。{f801}</source>
    <target>君たちは魔力検知機を取り出し、{f801}使用してみる…。{f801}{f802}すると、魔力検知機の内部が{f801}カチャカチャと音を立て始める。{f801}{f802}やがてカチャカチャという音は止まり、{f801}代わりに小気味いいチーンッという音が{f801}部屋の中に鳴り響く。{f801}{f802}どうやら検知が終了したようだ。{f801}君たちはどれどれと、いくつ反応が{f801}返ってきたか確認してみる…。{f801}{f802}反応を示すランプには光が{f804}{0500}{f810}{0000}つ{f804}{0000}{f801}灯っている!{f801}{f802}どうやら今の君たちの周りには{f804}{0500}{f810}{0000}つ{f804}{0000}の{f801}罠が埋まっているようだ。{f801}{f802}君たちは今得た情報を元に{f801}次の行動に出る必要がある。{f801}</target>
  </entry>
  <entry id="40">
    <source>{f804}{0500}誰に頼みますか?{f804}{0000}{f801}</source>
    <target>{f804}{0500}誰に頼みますか?{f804}{0000}{f801}</target>
  </entry>
  <entry id="41">
    <source>罠の感知を任された{f843}{0000}は{f801}自信ありげに頷くと、目を閉じる。{f801}{f802}そして、静かに呼吸をしながら、{f801}自分たちの周りにある魔力の反応を{f801}探っていく。{f801}{f802}少しだけ時間が経つと、{f843}{0000}は{f801}目を開き、待っていた君たちの方に{f801}向き直る。{f801}{f802}しかし、{f843}{0000}は自分たちを{f801}中心にした隣の1マス内には魔力の反応は{f801}見つからないという。{f801}{f802}であれば、君たちは別の場所に立ち、{f801}罠の在りかを探す作業を続ける必要がある。{f801}</source>
    <target>罠の感知を任された{f843}{0000}は{f801}自信ありげに頷くと、目を閉じる。{f801}{f802}そして、静かに呼吸をしながら、{f801}自分たちの周りにある魔力の反応を{f801}探っていく。{f801}{f802}少しだけ時間が経つと、{f843}{0000}は{f801}目を開き、待っていた君たちの方に{f801}向き直る。{f801}{f802}しかし、{f843}{0000}は自分たちを{f801}中心にした隣の1マス内には魔力の反応は{f801}見つからないという。{f801}{f802}であれば、君たちは別の場所に立ち、{f801}罠の在りかを探す作業を続ける必要がある。{f801}</target>
  </entry>
  <entry id="42">
    <source>罠の感知を任された{f843}{0000}は{f801}自信ありげに頷くと、目を閉じる。{f801}{f802}そして、静かに呼吸をしながら、{f801}自分たちの周りにある魔力の反応を{f801}探っていく。{f801}{f802}少しだけ時間が経つと、{f843}{0000}は{f801}目を開き、待っていた君たちの方に{f801}向き直る。{f801}{f802}{f843}{0000}が言うには{f801}{f804}{0500}北に{f804}{0000}魔力の反応があるという。{f801}{f802}君たちはその情報を元に{f801}次の行動に出る必要がある。{f801}</source>
    <target>罠の感知を任された{f843}{0000}は{f801}自信ありげに頷くと、目を閉じる。{f801}{f802}そして、静かに呼吸をしながら、{f801}自分たちの周りにある魔力の反応を{f801}探っていく。{f801}{f802}少しだけ時間が経つと、{f843}{0000}は{f801}目を開き、待っていた君たちの方に{f801}向き直る。{f801}{f802}{f843}{0000}が言うには{f801}{f804}{0500}北に{f804}{0000}魔力の反応があるという。{f801}{f802}君たちはその情報を元に{f801}次の行動に出る必要がある。{f801}</target>
  </entry>
  <entry id="43">
    <source>罠の感知を任された{f843}{0000}は{f801}自信ありげに頷くと、目を閉じる。{f801}{f802}そして、静かに呼吸をしながら、{f801}自分たちの周りにある魔力の反応を{f801}探っていく。{f801}{f802}少しだけ時間が経つと、{f843}{0000}は{f801}目を開き、待っていた君たちの方に{f801}向き直る。{f801}{f802}{f843}{0000}が言うには{f801}{f804}{0500}南に{f804}{0000}魔力の反応があるという。{f801}{f802}君たちはその情報を元に{f801}次の行動に出る必要がある。{f801}</source>
    <target>罠の感知を任された{f843}{0000}は{f801}自信ありげに頷くと、目を閉じる。{f801}{f802}そして、静かに呼吸をしながら、{f801}自分たちの周りにある魔力の反応を{f801}探っていく。{f801}{f802}少しだけ時間が経つと、{f843}{0000}は{f801}目を開き、待っていた君たちの方に{f801}向き直る。{f801}{f802}{f843}{0000}が言うには{f801}{f804}{0500}南に{f804}{0000}魔力の反応があるという。{f801}{f802}君たちはその情報を元に{f801}次の行動に出る必要がある。{f801}</target>
  </entry>
  <entry id="44">
    <source>罠の感知を任された{f843}{0000}は{f801}自信ありげに頷くと、目を閉じる。{f801}{f802}そして、静かに呼吸をしながら、{f801}自分たちの周りにある魔力の反応を{f801}探っていく。{f801}{f802}少しだけ時間が経つと、{f843}{0000}は{f801}目を開き、待っていた君たちの方に{f801}向き直る。{f801}{f802}{f843}{0000}が言うには{f801}{f804}{0500}東に{f804}{0000}魔力の反応があるという。{f801}{f802}君たちはその情報を元に{f801}次の行動に出る必要がある。{f801}</source>
    <target>罠の感知を任された{f843}{0000}は{f801}自信ありげに頷くと、目を閉じる。{f801}{f802}そして、静かに呼吸をしながら、{f801}自分たちの周りにある魔力の反応を{f801}探っていく。{f801}{f802}少しだけ時間が経つと、{f843}{0000}は{f801}目を開き、待っていた君たちの方に{f801}向き直る。{f801}{f802}{f843}{0000}が言うには{f801}{f804}{0500}東に{f804}{0000}魔力の反応があるという。{f801}{f802}君たちはその情報を元に{f801}次の行動に出る必要がある。{f801}</target>
  </entry>
  <entry id="45">
    <source>罠の感知を任された{f843}{0000}は{f801}自信ありげに頷くと、目を閉じる。{f801}{f802}そして、静かに呼吸をしながら、{f801}自分たちの周りにある魔力の反応を{f801}探っていく。{f801}{f802}少しだけ時間が経つと、{f843}{0000}は{f801}目を開き、待っていた君たちの方に{f801}向き直る。{f801}{f802}{f843}{0000}が言うには{f801}{f804}{0500}西に{f804}{0000}魔力の反応があるという。{f801}{f802}君たちはその情報を元に{f801}次の行動に出る必要がある。{f801}</source>
    <target>罠の感知を任された{f843}{0000}は{f801}自信ありげに頷くと、目を閉じる。{f801}{f802}そして、静かに呼吸をしながら、{f801}自分たちの周りにある魔力の反応を{f801}探っていく。{f801}{f802}少しだけ時間が経つと、{f843}{0000}は{f801}目を開き、待っていた君たちの方に{f801}向き直る。{f801}{f802}{f843}{0000}が言うには{f801}{f804}{0500}西に{f804}{0000}魔力の反応があるという。{f801}{f802}君たちはその情報を元に{f801}次の行動に出る必要がある。{f801}</target>
  </entry>
  <entry id="46">
    <source>罠の感知を任された{f843}{0000}は{f801}自信ありげに頷くと、目を閉じる。{f801}{f802}そして、静かに呼吸をしながら、{f801}自分たちの周りにある魔力の反応を{f801}探っていく。{f801}{f802}少しだけ時間が経つと、{f843}{0000}は{f801}目を開き、待っていた君たちの方に{f801}向き直る。{f801}{f802}{f843}{0000}が言うには{f801}{f804}{0500}南と東に{f804}{0000}魔力の反応があるという。{f801}{f802}君たちはその情報を元に{f801}次の行動に出る必要がある。{f801}</source>
    <target>罠の感知を任された{f843}{0000}は{f801}自信ありげに頷くと、目を閉じる。{f801}{f802}そして、静かに呼吸をしながら、{f801}自分たちの周りにある魔力の反応を{f801}探っていく。{f801}{f802}少しだけ時間が経つと、{f843}{0000}は{f801}目を開き、待っていた君たちの方に{f801}向き直る。{f801}{f802}{f843}{0000}が言うには{f801}{f804}{0500}南と東に{f804}{0000}魔力の反応があるという。{f801}{f802}君たちはその情報を元に{f801}次の行動に出る必要がある。{f801}</target>
  </entry>
  <entry id="47">
    <source>罠の感知を任された{f843}{0000}は{f801}自信ありげに頷くと、目を閉じる。{f801}{f802}そして、静かに呼吸をしながら、{f801}自分たちの周りにある魔力の反応を{f801}探っていく。{f801}{f802}少しだけ時間が経つと、{f843}{0000}は{f801}目を開き、待っていた君たちの方に{f801}向き直る。{f801}{f802}{f843}{0000}が言うには{f801}{f804}{0500}北と西に{f804}{0000}魔力の反応があるという。{f801}{f802}君たちはその情報を元に{f801}次の行動に出る必要がある。{f801}</source>
    <target>罠の感知を任された{f843}{0000}は{f801}自信ありげに頷くと、目を閉じる。{f801}{f802}そして、静かに呼吸をしながら、{f801}自分たちの周りにある魔力の反応を{f801}探っていく。{f801}{f802}少しだけ時間が経つと、{f843}{0000}は{f801}目を開き、待っていた君たちの方に{f801}向き直る。{f801}{f802}{f843}{0000}が言うには{f801}{f804}{0500}北と西に{f804}{0000}魔力の反応があるという。{f801}{f802}君たちはその情報を元に{f801}次の行動に出る必要がある。{f801}</target>
  </entry>
  <entry id="48">
    <source>罠の感知を任された{f843}{0000}は{f801}自信ありげに頷くと、目を閉じる。{f801}{f802}そして、静かに呼吸をしながら、{f801}自分たちの周りにある魔力の反応を{f801}探っていく。{f801}{f802}少しだけ時間が経つと、{f843}{0000}は{f801}目を開き、待っていた君たちの方に{f801}向き直る。{f801}{f802}だが、その表情には苦笑いが張り付いており{f801}魔力の反応なんてさっぱり感じ取れないと{f801}いってきた。{f801}{f802}{f843}{0000}には魔力を感知する力が{f801}ないのだから、こうなるのは自明の理だ。{f801}{f802}君たちは改めて、この後どうするのかを{f801}考える必要がある。{f801}</source>
    <target>罠の感知を任された{f843}{0000}は{f801}自信ありげに頷くと、目を閉じる。{f801}{f802}そして、静かに呼吸をしながら、{f801}自分たちの周りにある魔力の反応を{f801}探っていく。{f801}{f802}少しだけ時間が経つと、{f843}{0000}は{f801}目を開き、待っていた君たちの方に{f801}向き直る。{f801}{f802}だが、その表情には苦笑いが張り付いており{f801}魔力の反応なんてさっぱり感じ取れないと{f801}いってきた。{f801}{f802}{f843}{0000}には魔力を感知する力が{f801}ないのだから、こうなるのは自明の理だ。{f801}{f802}君たちは改めて、この後どうするのかを{f801}考える必要がある。{f801}</target>
  </entry>
  <entry id="50">
    <source>罠の解除作業の前にひとつ確認しておく。{f801}{f802}君たちが持っている魔力吸収のお札は{f801}{f804}{0500}5つしかない{f804}{0000}。{f801}{f802}使うべきところを間違い続ければ、{f801}お札が足りなくなり、自分たちで罠を{f801}踏み抜く強硬手段を選ぶ必要が出てくる。{f801}{f802}もしくはクエストを破棄して、{f801}最初からやり直すかだ。{f801}{f802}それが理解できたのなら、{f801}罠がどこにあるのか、君たちは{f801}行動で示すといいだろう。{f801}</source>
    <target>罠の解除作業の前にひとつ確認しておく。{f801}{f802}君たちが持っている魔力吸収のお札は{f801}{f804}{0500}5つしかない{f804}{0000}。{f801}{f802}使うべきところを間違い続ければ、{f801}お札が足りなくなり、自分たちで罠を{f801}踏み抜く強硬手段を選ぶ必要が出てくる。{f801}{f802}もしくはクエストを破棄して、{f801}最初からやり直すかだ。{f801}{f802}それが理解できたのなら、{f801}罠がどこにあるのか、君たちは{f801}行動で示すといいだろう。{f801}</target>
  </entry>
  <entry id="51">
    <source>{f804}{0500}罠はどの方角にありますか?{f804}{0000}{f801}北{f801}南{f801}東{f801}西{f801}</source>
    <target>{f804}{0500}罠はどの方角にありますか?{f804}{0000}{f801}北{f801}南{f801}東{f801}西{f801}</target>
  </entry>
  <entry id="52">
    <source>{f804}{0500}北にお札を貼りますが、よろしいですか?{f804}{0000}{f801}貼る{f801}考え直す{f801}</source>
    <target>{f804}{0500}北にお札を貼りますが、よろしいですか?{f804}{0000}{f801}貼る{f801}考え直す{f801}</target>
  </entry>
  <entry id="53">
    <source>{f804}{0500}南にお札を貼りますが、よろしいですか?{f804}{0000}{f801}貼る{f801}考え直す{f801}</source>
    <target>{f804}{0500}南にお札を貼りますが、よろしいですか?{f804}{0000}{f801}貼る{f801}考え直す{f801}</target>
  </entry>
  <entry id="54">
    <source>{f804}{0500}東にお札を貼りますが、よろしいですか?{f804}{0000}{f801}貼る{f801}考え直す{f801}</source>
    <target>{f804}{0500}東にお札を貼りますが、よろしいですか?{f804}{0000}{f801}貼る{f801}考え直す{f801}</target>
  </entry>
  <entry id="55">
    <source>{f804}{0500}西にお札を貼りますが、よろしいですか?{f804}{0000}{f801}貼る{f801}考え直す{f801}</source>
    <target>{f804}{0500}西にお札を貼りますが、よろしいですか?{f804}{0000}{f801}貼る{f801}考え直す{f801}</target>
  </entry>
  <entry id="56">
    <source>君たちは間違いはないはずだと、{f801}その方角の地面にお札を貼り付ける。{f801}{f802}……。{f801}{f802}すると、地面から青白く魔法陣が{f801}浮かび上がり、お札へと吸い込まれるように{f801}消えていくではないか!{f801}{f802}やがて魔法陣はすっかりお札へと飲み込まれ{f801}辺りはいつもの景観を取り戻した。{f801}{f802}君たちは無事隠されていた罠を{f801}一つ解除することに成功したのだ!{f801}</source>
    <target>君たちは間違いはないはずだと、{f801}その方角の地面にお札を貼り付ける。{f801}{f802}……。{f801}{f802}すると、地面から青白く魔法陣が{f801}浮かび上がり、お札へと吸い込まれるように{f801}消えていくではないか!{f801}{f802}やがて魔法陣はすっかりお札へと飲み込まれ{f801}辺りはいつもの景観を取り戻した。{f801}{f802}君たちは無事隠されていた罠を{f801}一つ解除することに成功したのだ!{f801}</target>
  </entry>
  <entry id="57">
    <source>しかし、罠はまだ残っている。{f801}君たちはそのまま残りを解除するために{f801}行動を開始する必要がある。{f801}</source>
    <target>しかし、罠はまだ残っている。{f801}君たちはそのまま残りを解除するために{f801}行動を開始する必要がある。{f801}</target>
  </entry>
  <entry id="58">
    <source>そう思って行動をしようとしたが、{f801}君たちは問題があることに気付く。{f801}{f802}そう、君たちの手元には{f801}もうお札が残っていないのだ。{f801}{f802}こうなると自分たちで罠を踏み抜いて{f801}解除するか、クエストを破棄して{f801}やり直すかしかない。{f801}{f802}君たちはどうするかを決断したなら、{f801}それを行動に移すといいだろう。{f801}</source>
    <target>そう思って行動をしようとしたが、{f801}君たちは問題があることに気付く。{f801}{f802}そう、君たちの手元には{f801}もうお札が残っていないのだ。{f801}{f802}こうなると自分たちで罠を踏み抜いて{f801}解除するか、クエストを破棄して{f801}やり直すかしかない。{f801}{f802}君たちはどうするかを決断したなら、{f801}それを行動に移すといいだろう。{f801}</target>
  </entry>
  <entry id="59">
    <source>そして君たちは、今解除したものが{f801}罠の3つ目だったことに気付く。{f801}{f802}君たちは無事に依頼を達成したのだ!{f801}後は時間のある時に酒場へ行き、{f801}このことを報告するといいだろう。{f801}</source>
    <target>そして君たちは、今解除したものが{f801}罠の3つ目だったことに気付く。{f801}{f802}君たちは無事に依頼を達成したのだ!{f801}後は時間のある時に酒場へ行き、{f801}このことを報告するといいだろう。{f801}</target>
  </entry>
  <entry id="60">
    <source>君たちは間違いはないはずだと、{f801}その方角の地面にお札を貼り付ける。{f801}{f802}……。{f801}{f802}しかし、一切の反応が返って来ず、{f801}辺りは静寂に包まれたままだ。{f801}{f802}どうやらそこには罠など存在{f801}していなかったようだ…。{f801}{f802}そして、貼り付けたお札は既に{f801}効力を失ったようで、どことなく{f801}萎れてしまったような印象を受ける。{f801}</source>
    <target>君たちは間違いはないはずだと、{f801}その方角の地面にお札を貼り付ける。{f801}{f802}……。{f801}{f802}しかし、一切の反応が返って来ず、{f801}辺りは静寂に包まれたままだ。{f801}{f802}どうやらそこには罠など存在{f801}していなかったようだ…。{f801}{f802}そして、貼り付けたお札は既に{f801}効力を失ったようで、どことなく{f801}萎れてしまったような印象を受ける。{f801}</target>
  </entry>
  <entry id="61">
    <source>君たちは残りのお札を握りしめ、{f801}罠の解除するための行動を再び{f801}始める必要がある。{f801}</source>
    <target>君たちは残りのお札を握りしめ、{f801}罠の解除するための行動を再び{f801}始める必要がある。{f801}</target>
  </entry>
  <entry id="62">
    <source>さらに気付けば、君たちの手元には{f801}もう魔力吸収のお札は1つもない。{f801}{f802}こうなると自分たちで罠を踏み抜いて{f801}解除するか、クエストを破棄して{f801}やり直すかしかない。{f801}{f802}君たちはどうするかを決断したなら、{f801}それを行動に移すといいだろう。{f801}</source>
    <target>さらに気付けば、君たちの手元には{f801}もう魔力吸収のお札は1つもない。{f801}{f802}こうなると自分たちで罠を踏み抜いて{f801}解除するか、クエストを破棄して{f801}やり直すかしかない。{f801}{f802}君たちはどうするかを決断したなら、{f801}それを行動に移すといいだろう。{f801}</target>
  </entry>
  <entry id="63">
    <source>君たちはお札を貼ろうとするが、{f801}よく考えてみれば、そこには地面がない。{f801}つまり罠がある可能性もない。{f801}{f802}君たちは改めて罠の在りかを考えながら{f801}行動を再開しなくてはならない。{f801}</source>
    <target>君たちはお札を貼ろうとするが、{f801}よく考えてみれば、そこには地面がない。{f801}つまり罠がある可能性もない。{f801}{f802}君たちは改めて罠の在りかを考えながら{f801}行動を再開しなくてはならない。{f801}</target>
  </entry>
  <entry id="64">
    <source>残念ながら罠を解除するためのお札は{f801}もう君たちの手には残っていない。{f801}{f802}あきらめて自分たちで罠を踏み抜いて{f801}解除するか、クエストを破棄して{f801}やり直すかしかない。{f801}</source>
    <target>残念ながら罠を解除するためのお札は{f801}もう君たちの手には残っていない。{f801}{f802}あきらめて自分たちで罠を踏み抜いて{f801}解除するか、クエストを破棄して{f801}やり直すかしかない。{f801}</target>
  </entry>
  <entry id="65">
    <source>君たちは今すぐには行動には移さず、{f801}もう一度どこに罠が仕掛けられているのか{f801}考え直すことにする。{f801}</source>
    <target>君たちは今すぐには行動には移さず、{f801}もう一度どこに罠が仕掛けられているのか{f801}考え直すことにする。{f801}</target>
  </entry>
  <entry id="70">
    <source>君たちは今立っている場所で{f801}すべきことはないと判断して、{f801}何もしないことにした。{f801}</source>
    <target>君たちは今立っている場所で{f801}すべきことはないと判断して、{f801}何もしないことにした。{f801}</target>
  </entry>
</mbm>