<mbm>
  <entry id="1">
    <source>{f812}細い目をした薬師{0000}参った参った。{f801}まさかでかくなっただけと思ってた{f801}モグラに苦戦を強いられるとはね。{f801}{f802}アイツいきなり地面の中に潜っちゃってさ{f801}こっちの攻撃が当たらない当たらない。{f801}で、顔を出したと思えば手痛い攻撃。{f801}{f802}眠らせたり混乱させたり、後は脚を{f801}封じたりしたら潜らなくなるのかな。{f801}何にしても、生き残れて良かった〜。{f801}</source>
    <target>{f812}細い目をした薬師{0000}参った参った。{f801}まさかでかくなっただけと思ってた{f801}モグラに苦戦を強いられるとはね。{f801}{f802}アイツいきなり地面の中に潜っちゃってさ{f801}こっちの攻撃が当たらない当たらない。{f801}で、顔を出したと思えば手痛い攻撃。{f801}{f802}眠らせたり混乱させたり、後は脚を{f801}封じたりしたら潜らなくなるのかな。{f801}何にしても、生き残れて良かった〜。{f801}</target>
  </entry>
  <entry id="10">
    <source>{f812}細い目をした薬師{0000}ははは、まぁた困難な相手に会っちゃった。{f801}今度はどでかいオウム。{f801}{f802}身構えたとこに攻撃したら{f801}真似して反撃してくるんだよね。{f801}痛いオウム返しなんてホント勘弁だよ。{f801}{f802}でも、魔法攻撃には反撃してこなかったし{f801}電撃には弱い感じだったんだよねぇ。{f801}となると、そこを狙わない手はないね。{f801}</source>
    <target>{f812}細い目をした薬師{0000}ははは、まぁた困難な相手に会っちゃった。{f801}今度はどでかいオウム。{f801}{f802}身構えたとこに攻撃したら{f801}真似して反撃してくるんだよね。{f801}痛いオウム返しなんてホント勘弁だよ。{f801}{f802}でも、魔法攻撃には反撃してこなかったし{f801}電撃には弱い感じだったんだよねぇ。{f801}となると、そこを狙わない手はないね。{f801}</target>
  </entry>
  <entry id="20">
    <source>{f812}細い目をした薬師{0000}いてて、まさかあんな凶暴なゴリラが{f801}闊歩してるなんて思いもしなかったよ。{f801}{f802}仲間の言葉を借りるなら、{f801}他の魔物より足は遅いけど、{f801}タフでパワフルでクレイジーな魔物だね。{f801}{f802}目を見えなくさせれば楽になるのかな?{f801}あ、腕を縛っちゃうのも良さそうだね。{f801}それにしても樹海は厳しいねぇ。{f801}</source>
    <target>{f812}細い目をした薬師{0000}いてて、まさかあんな凶暴なゴリラが{f801}闊歩してるなんて思いもしなかったよ。{f801}{f802}仲間の言葉を借りるなら、{f801}他の魔物より足は遅いけど、{f801}タフでパワフルでクレイジーな魔物だね。{f801}{f802}目を見えなくさせれば楽になるのかな?{f801}あ、腕を縛っちゃうのも良さそうだね。{f801}それにしても樹海は厳しいねぇ。{f801}</target>
  </entry>
</mbm>