<mbm>
  <entry id="0">
    <source>{f859}{0300}{f813}{0b00}{0000}{9500}{0000}あぁ、その依頼引き受けるか?{f801}お前らと同じ冒険者からの依頼だが、{f801}別に抵抗はねぇか?{f801}{f802}まぁ商売敵でもあるが、{f801}同業者のよしみってヤツもあるわな、{f801}助けてやんのは良いことじゃねぇか?{f801}{f802}でな、そのギルドの連中{f801}この前新しい階層に入ったトコで{f801}ボロボロにやられちまったのさ。{f801}{f802}そん時ヤツラの連れてた{f801}錬金術師がやられてな、{f801}どうしても人が必要なんだと。{f801}{f802}{f813}{0b00}{0000}{8400}{0000}詳しいことは本人に聞いてくれや。{f801}ちょうど、あそこで飲んでるからな。{f801}</source>
    <target>{f859}{0300}{f813}{0b00}{0000}{9500}{0000}啊哈，要接受那个任务吗?{f801}虽然是跟你们一样的冒险者发布的任务，{f801}但是并没有啥抵抗吧?{f801}{f802}嘛虽说是商业敌人，{f801}但也有同业者的友谊什么的，{f801}能帮到对方也是件好事不是吗?{f801}{f802}那么，工会那帮家伙{f801}在之前进入了新的阶层{f801}结果被打得满头包。{f801}{f802}那会他们带的{f801}炼金术师被干掉了，{f801}总之就需要人去帮他们。{f801}{f802}{f813}{0b00}{0000}{8400}{0000}详细的事就去问本人吧。{f801}就在那边喝着的那群。{f801}</target>
  </entry>
  <entry id="1">
    <source>{f859}{0300}{f813}{0b00}{0000}{8600}{0000}お、戻ってきたか。{f801}ちゃんと手を貸してやったか?{f801}貸しは作っておくと後から便利だぜ?{f801}{f802}だが、まぁこれであいつらんとこの{f801}錬金術師の姉ちゃんも心配事があるとか{f801}言ってたが安心できんだろ。{f801}{f802}{f813}{0b00}{0000}{9300}{0000}あん? いやな、さっき宿屋に行ったら{f801}ばったり出くわしちまってよ。{f801}だいぶ元気になったみたいで…。{f801}{f802}なんだお前ら呆けた顔して。{f801}仇討ち? いやいやいや、何言ってんだ。{f801}あの姉ちゃんなら生きてんぞ?{f801}{f802}{f813}{0b00}{0000}{9100}{0000}…あー、そういやあのギルドのリーダー、{f801}物事を大げさに言いまわす節があったな。{f801}あいつの言ってた心配事ってそれか…。{f801}{f802}ま、いいんじゃねぇか?{f801}あいつらはお目当ての魔物を倒せる。{f801}お前らは報酬を受け取れるってな。{f801}{f802}{f813}{0b00}{0000}{8200}{0000}ホラ、これが仇討ち協力の褒美だ。{f801}ちゃんと受け取れよ?{f801}はははははっ!{f801}</source>
    <target>{f859}{0300}{f813}{0b00}{0000}{8600}{0000}喔，回来啦。{f801}稍微帮了一下忙?{f801}有了人情后面也会变得方便?{f801}{f802}但是，嘛这样的话他们跟{f801}炼金术师姐姐后续{f801}也会有所顾忌把。{f801}{f802}{f813}{0b00}{0000}{9300}{0000}啊嗯?其实，刚才我去了一下旅馆{f801}结果就撞见了他们。{f801}已经回复的差不多的样子了……{f801}{f802}你这发呆的表情是什么意思。{f801}报仇?不不不，你在说啥啊。{f801}那位小姐还活着哦?{f801}{f802}{f813}{0b00}{0000}{9100}{0000}……啊〜，那个工会的队长，{f801}会把事情往大了说呢。{f801}他说的担心的事是这件事啊……{f801}{f802}嘛，这样不也蛮好的?{f801}他们能打倒目标魔物。{f801}你们能获得任务报酬。{f801}{f802}{f813}{0b00}{0000}{8200}{0000}看，这就是帮忙报仇的奖励。{f801}好好拿好了噢?{f801}哈哈哈哈哈哈!{f801}</target>
  </entry>
</mbm>