<mbm>
  <entry id="0">
    <source>ダミー{f801} {f801}</source>
    <target>ダミー{f801} {f801}</target>
  </entry>
  <entry id="1">
    <source>斧技が得意なソードマン。{f801}斧スキルと採集スキルを扱う。{f801}</source>
    <target>斧技が得意なソードマン。{f801}斧スキルと採集スキルを扱う。{f801}</target>
  </entry>
  <entry id="2">
    <source>剣技が得意なソードマン。{f801}剣スキルと物理防御スキルを扱う。{f801}</source>
    <target>剣技が得意なソードマン。{f801}剣スキルと物理防御スキルを扱う。{f801}</target>
  </entry>
  <entry id="3">
    <source>搦め手が得意なソードマン。{f801}追撃スキルとその他各種補助系、ブースト系スキルを扱う。{f801}</source>
    <target>搦め手が得意なソードマン。{f801}追撃スキルとその他各種補助系、ブースト系スキルを扱う。{f801}</target>
  </entry>
  <entry id="4">
    <source>未熟なソードマン。{f801}各系統の基本的なスキルのみを扱う。{f801}</source>
    <target>未熟なソードマン。{f801}各系統の基本的なスキルのみを扱う。{f801}</target>
  </entry>
  <entry id="5">
    <source>ダミー{f801} {f801}</source>
    <target>ダミー{f801} {f801}</target>
  </entry>
  <entry id="6">
    <source>戦闘支援が得意なレンジャー。{f801}素早さブースト系スキルを全般的に扱う。{f801}</source>
    <target>戦闘支援が得意なレンジャー。{f801}素早さブースト系スキルを全般的に扱う。{f801}</target>
  </entry>
  <entry id="7">
    <source>探索補助を得意とするレンジャー。{f801}危機感知系スキルや探索スキル等を扱う。{f801}</source>
    <target>探索補助を得意とするレンジャー。{f801}危機感知系スキルや探索スキル等を扱う。{f801}</target>
  </entry>
  <entry id="8">
    <source>弓技が得意なレンジャー。{f801}あらゆる弓技を扱う。{f801}</source>
    <target>弓技が得意なレンジャー。{f801}あらゆる弓技を扱う。{f801}</target>
  </entry>
  <entry id="9">
    <source>未熟なレンジャー。{f801}各系統の基本的なスキルのみを扱う。{f801}</source>
    <target>未熟なレンジャー。{f801}各系統の基本的なスキルのみを扱う。{f801}</target>
  </entry>
  <entry id="10">
    <source>ダミー{f801} {f801}</source>
    <target>ダミー{f801} {f801}</target>
  </entry>
  <entry id="11">
    <source>盾がなくても使えるスキルを得意とするパラディン。{f801}属性防御ブースト系やHPブースト系のスキルを扱う。{f801}</source>
    <target>盾がなくても使えるスキルを得意とするパラディン。{f801}属性防御ブースト系やHPブースト系のスキルを扱う。{f801}</target>
  </entry>
  <entry id="12">
    <source>基礎的な盾による防御が得意なパラディン。{f801}盾マスタリーの中位までのスキルを扱う。{f801}</source>
    <target>基礎的な盾による防御が得意なパラディン。{f801}盾マスタリーの中位までのスキルを扱う。{f801}</target>
  </entry>
  <entry id="13">
    <source>高位な盾スキルや挑発技などを得意とするパラディン。{f801}盾マスタリーの上位スキルと{f801}物理防御ブーストのスキルを扱う。{f801}</source>
    <target>高位な盾スキルや挑発技などを得意とするパラディン。{f801}盾マスタリーの上位スキルと{f801}物理防御ブーストのスキルを扱う。{f801}</target>
  </entry>
  <entry id="14">
    <source>未熟なパラディン。{f801}各系統の基本的なスキルのみを扱う。{f801}</source>
    <target>未熟なパラディン。{f801}各系統の基本的なスキルのみを扱う。{f801}</target>
  </entry>
  <entry id="15">
    <source>ダミー{f801} {f801}</source>
    <target>ダミー{f801} {f801}</target>
  </entry>
  <entry id="16">
    <source>鞭技が得意なダークハンター。{f801}あらゆる鞭スキルを扱う。{f801}</source>
    <target>鞭技が得意なダークハンター。{f801}あらゆる鞭スキルを扱う。{f801}</target>
  </entry>
  <entry id="17">
    <source>剣技が得意なダークハンター。{f801}あらゆる剣スキルと伐採スキルを扱う。{f801}</source>
    <target>剣技が得意なダークハンター。{f801}あらゆる剣スキルと伐採スキルを扱う。{f801}</target>
  </entry>
  <entry id="18">
    <source>支援や搦め手が得意なダークハンター。{f801}武器に依存しない支援スキル系を主に扱う。{f801}</source>
    <target>支援や搦め手が得意なダークハンター。{f801}武器に依存しない支援スキル系を主に扱う。{f801}</target>
  </entry>
  <entry id="19">
    <source>未熟なダークハンター。{f801}各系統の基本的なスキルのみを扱う。{f801}</source>
    <target>未熟なダークハンター。{f801}各系統の基本的なスキルのみを扱う。{f801}</target>
  </entry>
  <entry id="20">
    <source>ダミー{f801} {f801}</source>
    <target>ダミー{f801} {f801}</target>
  </entry>
  <entry id="21">
    <source>青眼の構えが得意なブシドー。{f801}青眼の構え及びHPTPブーストに関わるスキルを扱う。{f801}</source>
    <target>青眼の構えが得意なブシドー。{f801}青眼の構え及びHPTPブーストに関わるスキルを扱う。{f801}</target>
  </entry>
  <entry id="22">
    <source>居合の構えが得意なブシドー。{f801}刀マスタリー及び居合の構えに関わるスキルを扱う。{f801}</source>
    <target>居合の構えが得意なブシドー。{f801}刀マスタリー及び居合の構えに関わるスキルを扱う。{f801}</target>
  </entry>
  <entry id="23">
    <source>上段の構えが得意なブシドー。{f801}上段の構えや無双の構えに関わるスキルを主に扱う。{f801}</source>
    <target>上段の構えが得意なブシドー。{f801}上段の構えや無双の構えに関わるスキルを主に扱う。{f801}</target>
  </entry>
  <entry id="24">
    <source>未熟なブシドー。{f801}各系統の基本的なスキルのみを扱う。{f801}</source>
    <target>未熟なブシドー。{f801}各系統の基本的なスキルのみを扱う。{f801}</target>
  </entry>
  <entry id="25">
    <source>ダミー{f801} {f801}</source>
    <target>ダミー{f801} {f801}</target>
  </entry>
  <entry id="26">
    <source>基本的な回復スキルが得意なメディック。{f801}中位までの回復マスタリー系スキルを扱う。{f801}</source>
    <target>基本的な回復スキルが得意なメディック。{f801}中位までの回復マスタリー系スキルを扱う。{f801}</target>
  </entry>
  <entry id="27">
    <source>杖で殴ることを得意とするメディック。{f801}回復を捨て、物理に関わるスキルを重点的に扱う。{f801}</source>
    <target>杖で殴ることを得意とするメディック。{f801}回復を捨て、物理に関わるスキルを重点的に扱う。{f801}</target>
  </entry>
  <entry id="28">
    <source>高位な回復スキルと補助能力を持つメディック。{f801}扱いの難しい、高度な回復マスタリー系スキルと{f801}TP、属性防御ブースト系のスキルを扱う。{f801}</source>
    <target>高位な回復スキルと補助能力を持つメディック。{f801}扱いの難しい、高度な回復マスタリー系スキルと{f801}TP、属性防御ブースト系のスキルを扱う。{f801}</target>
  </entry>
  <entry id="29">
    <source>未熟なメディック。{f801}各系統の基本的なスキルのみを扱う。{f801}</source>
    <target>未熟なメディック。{f801}各系統の基本的なスキルのみを扱う。{f801}</target>
  </entry>
  <entry id="30">
    <source>ダミー{f801} {f801}</source>
    <target>ダミー{f801} {f801}</target>
  </entry>
  <entry id="31">
    <source>術式マスタリー下位のスキルが得意なアルケミスト。{f801}単体術式及び、その派生スキルを扱う。{f801}</source>
    <target>術式マスタリー下位のスキルが得意なアルケミスト。{f801}単体術式及び、その派生スキルを扱う。{f801}</target>
  </entry>
  <entry id="32">
    <source>術式マスタリー上位のスキルが得意なアルケミスト。{f801}全体術式等、術式マスタリー上位スキルと{f801}TPブースト系スキルを扱う。{f801}</source>
    <target>術式マスタリー上位のスキルが得意なアルケミスト。{f801}全体術式等、術式マスタリー上位スキルと{f801}TPブースト系スキルを扱う。{f801}</target>
  </entry>
  <entry id="33">
    <source>術掌による攻撃が得意なアルケミスト。{f801}術掌マスタリーのスキル全般と{f801}その他幾つかの探索、パッシブ系スキルを扱う。{f801}</source>
    <target>術掌による攻撃が得意なアルケミスト。{f801}術掌マスタリーのスキル全般と{f801}その他幾つかの探索、パッシブ系スキルを扱う。{f801}</target>
  </entry>
  <entry id="34">
    <source>未熟なアルケミスト。{f801}各系統の基本的なスキルのみを扱う。{f801}</source>
    <target>未熟なアルケミスト。{f801}各系統の基本的なスキルのみを扱う。{f801}</target>
  </entry>
  <entry id="35">
    <source>ダミー{f801} {f801}</source>
    <target>ダミー{f801} {f801}</target>
  </entry>
  <entry id="36">
    <source>弱体スキルが得意なカースメーカー。{f801}弱体系呪言スキルとパッシブ系スキルを主に扱う。{f801}</source>
    <target>弱体スキルが得意なカースメーカー。{f801}弱体系呪言スキルとパッシブ系スキルを主に扱う。{f801}</target>
  </entry>
  <entry id="37">
    <source>状態異常スキルが得意なカースメーカー。{f801}相手を状態異常にする呪言スキルを扱う。{f801}</source>
    <target>状態異常スキルが得意なカースメーカー。{f801}相手を状態異常にする呪言スキルを扱う。{f801}</target>
  </entry>
  <entry id="38">
    <source>生命と精神に干渉するスキルが得意なカースメーカー。{f801}テラー系スキル及びHP、抑制攻撃ブースト系の{f801}スキルを扱う。{f801}</source>
    <target>生命と精神に干渉するスキルが得意なカースメーカー。{f801}テラー系スキル及びHP、抑制攻撃ブースト系の{f801}スキルを扱う。{f801}</target>
  </entry>
  <entry id="39">
    <source>未熟なカースメーカー。{f801}各系統の基本的なスキルのみを扱う。{f801}</source>
    <target>未熟なカースメーカー。{f801}各系統の基本的なスキルのみを扱う。{f801}</target>
  </entry>
  <entry id="40">
    <source>ダミー{f801} {f801}</source>
    <target>ダミー{f801} {f801}</target>
  </entry>
  <entry id="41">
    <source>歌マスタリーと関係のないスキルばかり得意なバード。{f801}各種ブースト系のスキルを扱う。{f801}</source>
    <target>歌マスタリーと関係のないスキルばかり得意なバード。{f801}各種ブースト系のスキルを扱う。{f801}</target>
  </entry>
  <entry id="42">
    <source>属性に関わる歌が得意なバード。{f801}属性系の歌スキル全てを扱う。{f801}</source>
    <target>属性に関わる歌が得意なバード。{f801}属性系の歌スキル全てを扱う。{f801}</target>
  </entry>
  <entry id="43">
    <source>味方を支援する歌が得意なバード。{f801}味方の能力を引き上げる強化系の{f801}歌スキル全般を扱う。{f801}</source>
    <target>味方を支援する歌が得意なバード。{f801}味方の能力を引き上げる強化系の{f801}歌スキル全般を扱う。{f801}</target>
  </entry>
  <entry id="44">
    <source>未熟なバード。{f801}各系統の基本的なスキルのみを扱う。{f801}</source>
    <target>未熟なバード。{f801}各系統の基本的なスキルのみを扱う。{f801}</target>
  </entry>
  <entry id="45">
    <source>ダミー{f801} {f801}</source>
    <target>ダミー{f801} {f801}</target>
  </entry>
  <entry id="46">
    <source>銃に依存しないスキルが得意なガンナー。{f801}HP、TPブースト系のスキルを扱う。{f801}</source>
    <target>銃に依存しないスキルが得意なガンナー。{f801}HP、TPブースト系のスキルを扱う。{f801}</target>
  </entry>
  <entry id="47">
    <source>銃による属性攻撃が得意なガンナー。{f801}各種属性ショットを扱う。{f801}</source>
    <target>銃による属性攻撃が得意なガンナー。{f801}各種属性ショットを扱う。{f801}</target>
  </entry>
  <entry id="48">
    <source>銃による物理攻撃が得意なガンナー。{f801}各種物理系の銃スキルと{f801}物理攻撃ブースト系スキルを扱う。{f801}</source>
    <target>銃による物理攻撃が得意なガンナー。{f801}各種物理系の銃スキルと{f801}物理攻撃ブースト系スキルを扱う。{f801}</target>
  </entry>
  <entry id="49">
    <source>未熟なガンナー。{f801}各系統の基本的なスキルのみを扱う。{f801}</source>
    <target>未熟なガンナー。{f801}各系統の基本的なスキルのみを扱う。{f801}</target>
  </entry>
  <entry id="50">
    <source>ダミー{f801} {f801}</source>
    <target>ダミー{f801} {f801}</target>
  </entry>
  <entry id="51">
    <source>回復系の巫術が得意なドクトルマグス。{f801}ドクトルマグスの回復スキルのみを扱う。{f801}</source>
    <target>回復系の巫術が得意なドクトルマグス。{f801}ドクトルマグスの回復スキルのみを扱う。{f801}</target>
  </entry>
  <entry id="52">
    <source>剣術が得意なドクトルマグス。{f801}巫剣系のスキル全般を扱う。{f801}</source>
    <target>剣術が得意なドクトルマグス。{f801}巫剣系のスキル全般を扱う。{f801}</target>
  </entry>
  <entry id="53">
    <source>補助が得意なドクトルマグス。{f801}補助系の巫術とブーストスキルを扱う。{f801}</source>
    <target>補助が得意なドクトルマグス。{f801}補助系の巫術とブーストスキルを扱う。{f801}</target>
  </entry>
  <entry id="54">
    <source>未熟なドクトルマグス。{f801}各系統の基本的なスキルのみを扱う。{f801}</source>
    <target>未熟なドクトルマグス。{f801}各系統の基本的なスキルのみを扱う。{f801}</target>
  </entry>
  <entry id="55">
    <source>ダミー{f801} {f801}</source>
    <target>ダミー{f801} {f801}</target>
  </entry>
  <entry id="56">
    <source>獣らしく技巧に頼らないペット。{f801}各種ブースト系スキル全般を扱う。{f801}</source>
    <target>獣らしく技巧に頼らないペット。{f801}各種ブースト系スキル全般を扱う。{f801}</target>
  </entry>
  <entry id="57">
    <source>爪による攻撃を得意とするペット。{f801}爪マスタリー系のスキル全般を扱う。{f801}</source>
    <target>爪による攻撃を得意とするペット。{f801}爪マスタリー系のスキル全般を扱う。{f801}</target>
  </entry>
  <entry id="58">
    <source>主人への忠義心に溢れたペット。{f801}忠義マスタリー系のスキル全般を扱う。{f801}</source>
    <target>主人への忠義心に溢れたペット。{f801}忠義マスタリー系のスキル全般を扱う。{f801}</target>
  </entry>
  <entry id="59">
    <source>未熟なペット。{f801}各系統の基本的なスキルのみを扱う。{f801}</source>
    <target>未熟なペット。{f801}各系統の基本的なスキルのみを扱う。{f801}</target>
  </entry>
  <entry id="60">
    <source>ダミー{f801} {f801}</source>
    <target>ダミー{f801} {f801}</target>
  </entry>
  <entry id="61">
    <source>属性追撃や属性支援系スキルを得意とするプリンセス。{f801}TPブースト系スキル全般を扱う。{f801}</source>
    <target>属性追撃や属性支援系スキルを得意とするプリンセス。{f801}TPブースト系スキル全般を扱う。{f801}</target>
  </entry>
  <entry id="62">
    <source>号令を出すことを得意とするプリンセス。{f801}号令マスタリーの号令スキル等を扱う。{f801}</source>
    <target>号令を出すことを得意とするプリンセス。{f801}号令マスタリーの号令スキル等を扱う。{f801}</target>
  </entry>
  <entry id="63">
    <source>強化弱体を解除したりといった{f801}特殊なスキルを得意とするプリンセス。{f801}HPブースト系や、上位の号令マスタリースキルを扱う。{f801}</source>
    <target>強化弱体を解除したりといった{f801}特殊なスキルを得意とするプリンセス。{f801}HPブースト系や、上位の号令マスタリースキルを扱う。{f801}</target>
  </entry>
  <entry id="64">
    <source>未熟なプリンセス。{f801}各系統の基本的なスキルのみを扱う。{f801}</source>
    <target>未熟なプリンセス。{f801}各系統の基本的なスキルのみを扱う。{f801}</target>
  </entry>
  <entry id="65">
    <source>ダミー{f801} {f801}</source>
    <target>ダミー{f801} {f801}</target>
  </entry>
  <entry id="66">
    <source>武器を選ばないファフニール。{f801}各種パッシブ系スキルを主に扱う。{f801}</source>
    <target>武器を選ばないファフニール。{f801}各種パッシブ系スキルを主に扱う。{f801}</target>
  </entry>
  <entry id="67">
    <source>フォースゲージの操作に長けたファフニール。{f801}フォースマスタリのほぼ全てのスキルを扱う。{f801}</source>
    <target>フォースゲージの操作に長けたファフニール。{f801}フォースマスタリのほぼ全てのスキルを扱う。{f801}</target>
  </entry>
  <entry id="68">
    <source>卓越した剣技のファフニール。{f801}全ての剣マスタリー系スキルを扱う。{f801}</source>
    <target>卓越した剣技のファフニール。{f801}全ての剣マスタリー系スキルを扱う。{f801}</target>
  </entry>
  <entry id="69">
    <source>未熟なファフニール。{f801}各系統の基本的なスキルのみを扱う。{f801}</source>
    <target>未熟なファフニール。{f801}各系統の基本的なスキルのみを扱う。{f801}</target>
  </entry>
  <entry id="70">
    <source>ダミー{f801} {f801}</source>
    <target>ダミー{f801} {f801}</target>
  </entry>
  <entry id="71">
    <source>相手の攻撃を凌ぐことが得意なハイランダー。{f801}物理防御ブースト系スキルを主に扱う。{f801}</source>
    <target>相手の攻撃を凌ぐことが得意なハイランダー。{f801}物理防御ブースト系スキルを主に扱う。{f801}</target>
  </entry>
  <entry id="72">
    <source>敵の撃破に役立つスキルが得意なハイランダー。{f801}物理攻撃ブースト系及びHPブースト系スキルを扱う。{f801}</source>
    <target>敵の撃破に役立つスキルが得意なハイランダー。{f801}物理攻撃ブースト系及びHPブースト系スキルを扱う。{f801}</target>
  </entry>
  <entry id="73">
    <source>槍の扱いに長けたハイランダー。{f801}全ての槍マスタリー系スキルを扱う。{f801}</source>
    <target>槍の扱いに長けたハイランダー。{f801}全ての槍マスタリー系スキルを扱う。{f801}</target>
  </entry>
  <entry id="74">
    <source>未熟なハイランダー。{f801}各系統の基本的なスキルのみを扱う。{f801}</source>
    <target>未熟なハイランダー。{f801}各系統の基本的なスキルのみを扱う。{f801}</target>
  </entry>
  <entry id="75">
    <source>ダミー{f801} {f801}</source>
    <target>ダミー{f801} {f801}</target>
  </entry>
  <entry id="76">
    <source>かつて数々の偉業を成し遂げ、{f801}伝説とまで言われたソードマン。{f801}幻の付加効果がついたグリモアを所持している。{f801}</source>
    <target>かつて数々の偉業を成し遂げ、{f801}伝説とまで言われたソードマン。{f801}幻の付加効果がついたグリモアを所持している。{f801}</target>
  </entry>
  <entry id="77">
    <source>かつて数々の偉業を成し遂げ、{f801}伝説とまで言われたレンジャー。{f801}幻の付加効果がついたグリモアを所持している。{f801}</source>
    <target>かつて数々の偉業を成し遂げ、{f801}伝説とまで言われたレンジャー。{f801}幻の付加効果がついたグリモアを所持している。{f801}</target>
  </entry>
  <entry id="78">
    <source>かつて数々の偉業を成し遂げ、{f801}伝説とまで言われたパラディン。{f801}幻の付加効果がついたグリモアを所持している。{f801}</source>
    <target>かつて数々の偉業を成し遂げ、{f801}伝説とまで言われたパラディン。{f801}幻の付加効果がついたグリモアを所持している。{f801}</target>
  </entry>
  <entry id="79">
    <source>かつて数々の偉業を成し遂げ、{f801}伝説とまで言われたダークハンター。{f801}幻の付加効果がついたグリモアを所持している。{f801}</source>
    <target>かつて数々の偉業を成し遂げ、{f801}伝説とまで言われたダークハンター。{f801}幻の付加効果がついたグリモアを所持している。{f801}</target>
  </entry>
  <entry id="80">
    <source>かつて数々の偉業を成し遂げ、{f801}伝説とまで言われたメディック。{f801}幻の付加効果がついたグリモアを所持している。{f801}</source>
    <target>かつて数々の偉業を成し遂げ、{f801}伝説とまで言われたメディック。{f801}幻の付加効果がついたグリモアを所持している。{f801}</target>
  </entry>
  <entry id="81">
    <source>かつて数々の偉業を成し遂げ、{f801}伝説とまで言われたブシドー。{f801}幻の付加効果がついたグリモアを所持している。{f801}</source>
    <target>かつて数々の偉業を成し遂げ、{f801}伝説とまで言われたブシドー。{f801}幻の付加効果がついたグリモアを所持している。{f801}</target>
  </entry>
  <entry id="82">
    <source>かつて数々の偉業を成し遂げ、{f801}伝説とまで言われたアルケミスト。{f801}幻の付加効果がついたグリモアを所持している。{f801}</source>
    <target>かつて数々の偉業を成し遂げ、{f801}伝説とまで言われたアルケミスト。{f801}幻の付加効果がついたグリモアを所持している。{f801}</target>
  </entry>
  <entry id="83">
    <source>かつて数々の偉業を成し遂げ、{f801}伝説とまで言われたカースメーカー。{f801}幻の付加効果がついたグリモアを所持している。{f801}</source>
    <target>かつて数々の偉業を成し遂げ、{f801}伝説とまで言われたカースメーカー。{f801}幻の付加効果がついたグリモアを所持している。{f801}</target>
  </entry>
  <entry id="84">
    <source>かつて数々の偉業を成し遂げ、{f801}伝説とまで言われたバード。{f801}幻の付加効果がついたグリモアを所持している。{f801}</source>
    <target>かつて数々の偉業を成し遂げ、{f801}伝説とまで言われたバード。{f801}幻の付加効果がついたグリモアを所持している。{f801}</target>
  </entry>
  <entry id="85">
    <source>かつて数々の偉業を成し遂げ、{f801}伝説とまで言われたガンナー。{f801}幻の付加効果がついたグリモアを所持している。{f801}</source>
    <target>かつて数々の偉業を成し遂げ、{f801}伝説とまで言われたガンナー。{f801}幻の付加効果がついたグリモアを所持している。{f801}</target>
  </entry>
  <entry id="86">
    <source>かつて数々の偉業を成し遂げ、{f801}伝説とまで言われたドクトルマグス。{f801}幻の付加効果がついたグリモアを所持している。{f801}</source>
    <target>かつて数々の偉業を成し遂げ、{f801}伝説とまで言われたドクトルマグス。{f801}幻の付加効果がついたグリモアを所持している。{f801}</target>
  </entry>
  <entry id="87">
    <source>かつて数々の偉業を成し遂げ、{f801}伝説とまで言われたペット。{f801}幻の付加効果がついたグリモアを所持している。{f801}</source>
    <target>かつて数々の偉業を成し遂げ、{f801}伝説とまで言われたペット。{f801}幻の付加効果がついたグリモアを所持している。{f801}</target>
  </entry>
  <entry id="88">
    <source>かつて数々の偉業を成し遂げ、{f801}伝説とまで言われたプリンセス。{f801}幻の付加効果がついたグリモアを所持している。{f801}</source>
    <target>かつて数々の偉業を成し遂げ、{f801}伝説とまで言われたプリンセス。{f801}幻の付加効果がついたグリモアを所持している。{f801}</target>
  </entry>
  <entry id="89">
    <source>かつて数々の偉業を成し遂げ、{f801}伝説とまで言われたファフニール。{f801}幻の付加効果がついたグリモアを所持している。{f801}</source>
    <target>かつて数々の偉業を成し遂げ、{f801}伝説とまで言われたファフニール。{f801}幻の付加効果がついたグリモアを所持している。{f801}</target>
  </entry>
  <entry id="90">
    <source>かつて数々の偉業を成し遂げ、{f801}伝説とまで言われたハイランダー。{f801}幻の付加効果がついたグリモアを所持している。{f801}</source>
    <target>かつて数々の偉業を成し遂げ、{f801}伝説とまで言われたハイランダー。{f801}幻の付加効果がついたグリモアを所持している。{f801}</target>
  </entry>
  <entry id="100">
    <source>かつて世界樹の迷宮にて{f801}{f811}{0100}として{f801}名を馳せた元冒険者。{f801}</source>
    <target>かつて世界樹の迷宮にて{f801}{f811}{0100}として{f801}名を馳せた元冒険者。{f801}</target>
  </entry>
</mbm>