<mbm>
  <entry id="0">
    <source>またこの季節が来たわよ。{f801}…ってあなたたち、討伐大会は{f801}初めてだったわね。{f801}{f802}ギルド長が冒険者の練度向上のために催す{f801}…まぁ、この街の冒険者たちの{f801}お祭りみたいなものね。{f801}{f802}指定された魔物をたくさん討伐して{f801}その合計数を他のギルドと競い合うの。{f801}</source>
    <target>またこの季節が来たわよ。{f801}…ってあなたたち、討伐大会は{f801}初めてだったわね。{f801}{f802}ギルド長が冒険者の練度向上のために催す{f801}…まぁ、この街の冒険者たちの{f801}お祭りみたいなものね。{f801}{f802}指定された魔物をたくさん討伐して{f801}その合計数を他のギルドと競い合うの。{f801}</target>
  </entry>
  <entry id="1">
    <source>頑張ってね!{f801}あなたたちの優勝を祈っているわ。{f801}それじゃ、お早いお帰りを。{f801}</source>
    <target>頑張ってね!{f801}あなたたちの優勝を祈っているわ。{f801}それじゃ、お早いお帰りを。{f801}</target>
  </entry>
  <entry id="2">
    <source>…ヤラカーナは…ダメね、あのギルドは{f801}ボンクラばっかりだし…やっぱりここは{f801}{f840}に……。{f801}{f802}あ、あらあなたたち!?{f801}いつからいらしていたの?{f801}その依頼ね? 討伐依頼よ、ええ!{f801}</source>
    <target>…ヤラカーナは…ダメね、あのギルドは{f801}ボンクラばっかりだし…やっぱりここは{f801}{f840}に……。{f801}{f802}あ、あらあなたたち!?{f801}いつからいらしていたの?{f801}その依頼ね? 討伐依頼よ、ええ!{f801}</target>
  </entry>
  <entry id="3">
    <source>いいこと? あなたたちには{f801}勝利の二文字以外はあり得ないのよ。{f801}私…あなたたちに大枚賭け…。{f801}{f802}………ゲフンゲフン!{f801}あらいやだ風邪かしら、ホホホ…。{f801}それじゃ、お早いお帰りを。{f801}</source>
    <target>いいこと? あなたたちには{f801}勝利の二文字以外はあり得ないのよ。{f801}私…あなたたちに大枚賭け…。{f801}{f802}………ゲフンゲフン!{f801}あらいやだ風邪かしら、ホホホ…。{f801}それじゃ、お早いお帰りを。{f801}</target>
  </entry>
  <entry id="4">
    <source>…アイツ…気に喰わないわ。{f801}強豪ギルド抱えてるからいい気になって…{f801}…って、あらその依頼ね?{f801}{f802}…討伐大会よ! 受けてくれるわね!{f801}今、よその酒場の店主が来て{f801}わざわざ、勝利宣言していったのよ!{f801}{f802}この依頼は冒険者同士の競い合いでも{f801}あるけど…酒場同士の競い合いでもあるの。{f801}…だから負けられないのよ。{f801}</source>
    <target>…アイツ…気に喰わないわ。{f801}強豪ギルド抱えてるからいい気になって…{f801}…って、あらその依頼ね?{f801}{f802}…討伐大会よ! 受けてくれるわね!{f801}今、よその酒場の店主が来て{f801}わざわざ、勝利宣言していったのよ!{f801}{f802}この依頼は冒険者同士の競い合いでも{f801}あるけど…酒場同士の競い合いでもあるの。{f801}…だから負けられないのよ。{f801}</target>
  </entry>
  <entry id="5">
    <source>頼んだわよ、{f840}。{f801}この店の命運、あなたたちに託すわ。{f801}行ってらっしゃい、お早いお帰りを。{f801}</source>
    <target>頼んだわよ、{f840}。{f801}この店の命運、あなたたちに託すわ。{f801}行ってらっしゃい、お早いお帰りを。{f801}</target>
  </entry>
  <entry id="6">
    <source>あなたたち、その依頼が気になるのね?{f801}いいや、冒険者だもの…気になっている{f801}はずに違いないわ!{f801}{f802}それはギルド長からの討伐大会の依頼よ。{f801}指定された魔物をたくさん討伐して{f801}その合計数を他のギルドと競い合うの。{f801}</source>
    <target>あなたたち、その依頼が気になるのね?{f801}いいや、冒険者だもの…気になっている{f801}はずに違いないわ!{f801}{f802}それはギルド長からの討伐大会の依頼よ。{f801}指定された魔物をたくさん討伐して{f801}その合計数を他のギルドと競い合うの。{f801}</target>
  </entry>
  <entry id="7">
    <source>それじゃあ頑張ってね。{f801}他の冒険者に負けるんじゃないわよ!{f801}では、お早いお帰りを。{f801}</source>
    <target>それじゃあ頑張ってね。{f801}他の冒険者に負けるんじゃないわよ!{f801}では、お早いお帰りを。{f801}</target>
  </entry>
  <entry id="9">
    <source>デファインを作るためのダミーだから{f801}気にしなくていいわ。{f801}</source>
    <target>デファインを作るためのダミーだから{f801}気にしなくていいわ。{f801}</target>
  </entry>
  <entry id="10">
    <source>デファインを作るためのダミーだから{f801}気にしなくていいわ。{f801}</source>
    <target>デファインを作るためのダミーだから{f801}気にしなくていいわ。{f801}</target>
  </entry>
  <entry id="11">
    <source>デファインを作るためのダミーだから{f801}気にしなくていいわ。{f801}</source>
    <target>デファインを作るためのダミーだから{f801}気にしなくていいわ。{f801}</target>
  </entry>
  <entry id="12">
    <source>お帰りなさい。{f801}初めての討伐大会はどうだったかしら?{f801}{f802}そうそう、入賞はできなかったけど{f801}ギルド長から、参加賞を預かってるわ。{f801}はい、受け取って頂戴。{f801}{f802}今回もご苦労様でした。{f801}次は必ず入賞よ!{f801}</source>
    <target>お帰りなさい。{f801}初めての討伐大会はどうだったかしら?{f801}{f802}そうそう、入賞はできなかったけど{f801}ギルド長から、参加賞を預かってるわ。{f801}はい、受け取って頂戴。{f801}{f802}今回もご苦労様でした。{f801}次は必ず入賞よ!{f801}</target>
  </entry>
  <entry id="13">
    <source>お帰りなさい。{f801}結果はぼちぼちだったみたいね。{f801}私の気分もぼちぼちよ…。{f801}{f802}でもまぁ、今回もご苦労様でした。{f801}次回は頑張りましょうね。{f801}はい、これが参加賞よ。{f801}</source>
    <target>お帰りなさい。{f801}結果はぼちぼちだったみたいね。{f801}私の気分もぼちぼちよ…。{f801}{f802}でもまぁ、今回もご苦労様でした。{f801}次回は頑張りましょうね。{f801}はい、これが参加賞よ。{f801}</target>
  </entry>
  <entry id="14">
    <source>お帰りなさい。{f801}結果はぼちぼちだったみたいね。{f801}私の気分もぼちぼちよ…。{f801}{f802}でもまぁ、今回もご苦労様でした。{f801}次回は頑張りましょうね。{f801}はい、これが参加賞よ。{f801}</source>
    <target>お帰りなさい。{f801}結果はぼちぼちだったみたいね。{f801}私の気分もぼちぼちよ…。{f801}{f802}でもまぁ、今回もご苦労様でした。{f801}次回は頑張りましょうね。{f801}はい、これが参加賞よ。{f801}</target>
  </entry>
  <entry id="15">
    <source>お帰りなさい。{f801}結果はぼちぼちだったみたいね。{f801}{f802}はい、これが今回の参加賞よ。{f801}受け取って頂戴。{f801}{f802}では、今回もご苦労様でした。{f801}次は必ず入賞よ!{f801}</source>
    <target>お帰りなさい。{f801}結果はぼちぼちだったみたいね。{f801}{f802}はい、これが今回の参加賞よ。{f801}受け取って頂戴。{f801}{f802}では、今回もご苦労様でした。{f801}次は必ず入賞よ!{f801}</target>
  </entry>
  <entry id="16">
    <source>お帰りなさい!{f801}あなたたち、聞いたわよ!{f801}3位に入賞したそうじゃない!{f801}{f802}初めてなのに、凄いわ。{f801}ギルド長のおじ様も大層驚いてたわよ。{f801}{f802}はい、これが3位入賞の賞品よ。{f801}遠慮せず受け取って頂戴。{f801}では、今回もお疲れ様でした。{f801}</source>
    <target>お帰りなさい!{f801}あなたたち、聞いたわよ!{f801}3位に入賞したそうじゃない!{f801}{f802}初めてなのに、凄いわ。{f801}ギルド長のおじ様も大層驚いてたわよ。{f801}{f802}はい、これが3位入賞の賞品よ。{f801}遠慮せず受け取って頂戴。{f801}では、今回もお疲れ様でした。{f801}</target>
  </entry>
  <entry id="17">
    <source>お帰りなさい!{f801}あなたたち、聞いたわよ!{f801}3位に入賞したそうじゃない!{f801}{f802}おめでとう!{f801}流石{f840}と言ったところ?{f801}おじ様から副賞も出ているのよ。{f801}{f802}それに、あなたたちが3位入賞なら{f801}私の方にも十分うまみが…{f801}…って、え? 何でもないデスヨ?{f801}{f802}とにかく、今度もお疲れ様でした。{f801}次も期待させてもらうわよ!{f801}</source>
    <target>お帰りなさい!{f801}あなたたち、聞いたわよ!{f801}3位に入賞したそうじゃない!{f801}{f802}おめでとう!{f801}流石{f840}と言ったところ?{f801}おじ様から副賞も出ているのよ。{f801}{f802}それに、あなたたちが3位入賞なら{f801}私の方にも十分うまみが…{f801}…って、え? 何でもないデスヨ?{f801}{f802}とにかく、今度もお疲れ様でした。{f801}次も期待させてもらうわよ!{f801}</target>
  </entry>
  <entry id="18">
    <source>お帰りなさい!{f801}あなたたち、聞いたわよ!{f801}3位に入賞したそうじゃない!{f801}{f802}おめでとう!{f801}流石{f840}と言ったところ?{f801}おじ様から副賞も出ているのよ。{f801}{f802}でも惜しかったわねぇ、もう少しであの{f801}性悪女の鼻を明かせるところだったのに…。{f801}{f802}とにかくお疲れ様でした。{f801}今日はゆっくり休んでね。{f801}それじゃ、またよろしくっ。{f801}</source>
    <target>お帰りなさい!{f801}あなたたち、聞いたわよ!{f801}3位に入賞したそうじゃない!{f801}{f802}おめでとう!{f801}流石{f840}と言ったところ?{f801}おじ様から副賞も出ているのよ。{f801}{f802}でも惜しかったわねぇ、もう少しであの{f801}性悪女の鼻を明かせるところだったのに…。{f801}{f802}とにかくお疲れ様でした。{f801}今日はゆっくり休んでね。{f801}それじゃ、またよろしくっ。{f801}</target>
  </entry>
  <entry id="19">
    <source>お帰りなさい!{f801}あなたたち、聞いたわよ!{f801}3位に入賞したそうじゃない!{f801}{f802}おめでとう!{f801}流石{f840}と言ったところ?{f801}おじ様から副賞も出ているのよ。{f801}</source>
    <target>お帰りなさい!{f801}あなたたち、聞いたわよ!{f801}3位に入賞したそうじゃない!{f801}{f802}おめでとう!{f801}流石{f840}と言ったところ?{f801}おじ様から副賞も出ているのよ。{f801}</target>
  </entry>
  <entry id="20">
    <source>それじゃ、いつもいつもありがとうね。{f801}今日はゆっくり休んで頂戴。{f801}今度もお疲れ様でした。{f801}</source>
    <target>それじゃ、いつもいつもありがとうね。{f801}今日はゆっくり休んで頂戴。{f801}今度もお疲れ様でした。{f801}</target>
  </entry>
  <entry id="21">
    <source>お帰りなさい!{f801}あなたたち、聞いたわよ!{f801}2位に入賞したそうじゃない!{f801}{f802}初めてなのに凄いわっ!{f801}やっぱり私が見込んだギルドね。{f801}おじ様も、褒めてたわよ。{f801}{f802}はい、これがお待ちかねの報酬よ。{f801}流石2位の賞品…豪華ねぇ。{f801}</source>
    <target>お帰りなさい!{f801}あなたたち、聞いたわよ!{f801}2位に入賞したそうじゃない!{f801}{f802}初めてなのに凄いわっ!{f801}やっぱり私が見込んだギルドね。{f801}おじ様も、褒めてたわよ。{f801}{f802}はい、これがお待ちかねの報酬よ。{f801}流石2位の賞品…豪華ねぇ。{f801}</target>
  </entry>
  <entry id="22">
    <source>お帰りなさい!{f801}あなたたち、聞いたわよ!{f801}2位に入賞したそうじゃない!{f801}{f802}おめでとう!{f801}流石{f840}と言ったところ?{f801}おじ様から副賞も出ているのよ。{f801}{f802}それに、あなたたちが2位入賞なら{f801}私の方にもかなりのうまみが…{f801}…って、え? 何でもないデスヨ?{f801}{f802}とにかく、今度もお疲れ様でした。{f801}次も期待させてもらうわよ!{f801}</source>
    <target>お帰りなさい!{f801}あなたたち、聞いたわよ!{f801}2位に入賞したそうじゃない!{f801}{f802}おめでとう!{f801}流石{f840}と言ったところ?{f801}おじ様から副賞も出ているのよ。{f801}{f802}それに、あなたたちが2位入賞なら{f801}私の方にもかなりのうまみが…{f801}…って、え? 何でもないデスヨ?{f801}{f802}とにかく、今度もお疲れ様でした。{f801}次も期待させてもらうわよ!{f801}</target>
  </entry>
  <entry id="23">
    <source>お帰りなさい!{f801}あなたたち、聞いたわよ!{f801}2位に入賞したそうじゃない!{f801}{f802}おめでとう!{f801}流石{f840}と言ったところ?{f801}おじ様から副賞も出ているのよ。{f801}{f802}でも惜しかったわねぇ、もう少しであの{f801}性悪女の鼻を明かせるところだったのに…。{f801}{f802}とにかくお疲れ様でした。{f801}今日はゆっくり休んでね。{f801}それじゃ、またよろしくっ。{f801}</source>
    <target>お帰りなさい!{f801}あなたたち、聞いたわよ!{f801}2位に入賞したそうじゃない!{f801}{f802}おめでとう!{f801}流石{f840}と言ったところ?{f801}おじ様から副賞も出ているのよ。{f801}{f802}でも惜しかったわねぇ、もう少しであの{f801}性悪女の鼻を明かせるところだったのに…。{f801}{f802}とにかくお疲れ様でした。{f801}今日はゆっくり休んでね。{f801}それじゃ、またよろしくっ。{f801}</target>
  </entry>
  <entry id="24">
    <source>お帰りなさい!{f801}あなたたち、聞いたわよ!{f801}2位に入賞したそうじゃない!{f801}{f802}おめでとう!{f801}流石{f840}と言ったところ?{f801}私も鼻が高いわー。{f801}</source>
    <target>お帰りなさい!{f801}あなたたち、聞いたわよ!{f801}2位に入賞したそうじゃない!{f801}{f802}おめでとう!{f801}流石{f840}と言ったところ?{f801}私も鼻が高いわー。{f801}</target>
  </entry>
  <entry id="25">
    <source>それじゃ、いつもいつもありがとうね。{f801}今日はゆっくり休んで頂戴。{f801}今度もお疲れ様でした。{f801}</source>
    <target>それじゃ、いつもいつもありがとうね。{f801}今日はゆっくり休んで頂戴。{f801}今度もお疲れ様でした。{f801}</target>
  </entry>
  <entry id="26">
    <source>きゃーっ! 帰ってきた!{f801}お帰りなさい、あなたたち!{f801}{f802}優勝おめでとう、{f840}!{f801}やっぱりあなたたちは最高の冒険者ね!{f801}初めてなのに凄いわ。{f801}{f802}それにおじ様から、優勝賞品も出てるのよ。{f801}流石に豪華ねぇ…。{f801}尻込みしないで、受け取っちゃいなさい。{f801}</source>
    <target>きゃーっ! 帰ってきた!{f801}お帰りなさい、あなたたち!{f801}{f802}優勝おめでとう、{f840}!{f801}やっぱりあなたたちは最高の冒険者ね!{f801}初めてなのに凄いわ。{f801}{f802}それにおじ様から、優勝賞品も出てるのよ。{f801}流石に豪華ねぇ…。{f801}尻込みしないで、受け取っちゃいなさい。{f801}</target>
  </entry>
  <entry id="27">
    <source>きゃーっ! 帰ってきた!{f801}お帰りなさい、あなたたち!{f801}{f802}優勝おめでとう、{f840}!{f801}やっぱりあなたたちは最高の冒険者ね!{f801}おかげで私も何故かホクホクよ。{f801}{f802}ホクホクだから今日は私のおごりよ!{f801}さぁ、パーッとやっていきなさい!{f801}</source>
    <target>きゃーっ! 帰ってきた!{f801}お帰りなさい、あなたたち!{f801}{f802}優勝おめでとう、{f840}!{f801}やっぱりあなたたちは最高の冒険者ね!{f801}おかげで私も何故かホクホクよ。{f801}{f802}ホクホクだから今日は私のおごりよ!{f801}さぁ、パーッとやっていきなさい!{f801}</target>
  </entry>
  <entry id="28">
    <source>きゃーっ! 帰ってきた!{f801}お帰りなさい、あなたたち!{f801}{f802}店の外の『王者が集う店』って看板見た?{f801}王者っていうのはあなたたちのことよ!{f801}優勝の報せを聞いて、急いで作ったの!{f801}{f802}私の鼻の高さも天井知らずよっ!{f801}</source>
    <target>きゃーっ! 帰ってきた!{f801}お帰りなさい、あなたたち!{f801}{f802}店の外の『王者が集う店』って看板見た?{f801}王者っていうのはあなたたちのことよ!{f801}優勝の報せを聞いて、急いで作ったの!{f801}{f802}私の鼻の高さも天井知らずよっ!{f801}</target>
  </entry>
  <entry id="29">
    <source>きゃーっ! 帰ってきた!{f801}お帰りなさい、あなたたち!{f801}{f802}街中があなたたちのことを噂してるわ!{f801}今度の討伐大会の優勝ギルドは{f801}あなたたちだって!{f801}{f802}流石は{f840}ね!{f801}もうこのタルシスには、あなたたちに勝る{f801}冒険者はいないんじゃないかしら?{f801}</source>
    <target>きゃーっ! 帰ってきた!{f801}お帰りなさい、あなたたち!{f801}{f802}街中があなたたちのことを噂してるわ!{f801}今度の討伐大会の優勝ギルドは{f801}あなたたちだって!{f801}{f802}流石は{f840}ね!{f801}もうこのタルシスには、あなたたちに勝る{f801}冒険者はいないんじゃないかしら?{f801}</target>
  </entry>
  <entry id="30">
    <source>君たちが依頼の通りに{f804}{0500}{f847}{f804}{0000}を{f801}訪れると、側に控えていた兵士が{f801}声をかけてくる。{f801}</source>
    <target>君たちが依頼の通りに{f804}{0500}{f847}{f804}{0000}を{f801}訪れると、側に控えていた兵士が{f801}声をかけてくる。{f801}</target>
  </entry>
  <entry id="31">
    <source>「君たちは…孔雀亭からエントリーした{f801}{f840}だね?」{f801}</source>
    <target>「君たちは…孔雀亭からエントリーした{f801}{f840}だね?」{f801}</target>
  </entry>
  <entry id="32">
    <source>「この討伐大会は冒険者ギルドから{f801}各地の酒場を通して、タルシスの{f801}全冒険者に通達されているんだ」{f801}{f802}「君たちにはこのフロアに出現する{f801}{f804}{0500}{f848}{0000}{f804}{0000}と{f804}{0500}{f848}{0100}{f804}{0000}を{f801}倒せるだけ倒してほしい」{f801}{f802}「本クエストは、冒険者同士が互いに{f801}競い合い、練度を高めるのが目的だ。{f801}故に順位制を導入させてもらっている」{f801}{f802}「二種類の魔物を倒した総数で{f801}順位を決定するんだ。{f801}他のギルドに負けぬよう、頑張ってね」{f801}{f802}{f804}{0500}「それと一度でもこのフロアから出るか{f801}{f804}{0600}アリアドネの糸{f804}{0000}などで街に戻ったら{f801}その時点で集計が始まり大会は終了だ」{f801}{f804}{0000}{f802}「そのときに討伐数が10体未満だった{f801}場合はクエスト失敗となるので要注意だ」{f801}{f802}「クエストを終えたら、{f801}冒険者ギルドに赴き、ギルド長に{f801}君たちの順位を聞くといい」{f801}{f802}「説明は以上だが何か質問はある?{f801}…なければ、今回の討伐大会を{f801}始めさせてもらうよ」{f801}</source>
    <target>「この討伐大会は冒険者ギルドから{f801}各地の酒場を通して、タルシスの{f801}全冒険者に通達されているんだ」{f801}{f802}「君たちにはこのフロアに出現する{f801}{f804}{0500}{f848}{0000}{f804}{0000}と{f804}{0500}{f848}{0100}{f804}{0000}を{f801}倒せるだけ倒してほしい」{f801}{f802}「本クエストは、冒険者同士が互いに{f801}競い合い、練度を高めるのが目的だ。{f801}故に順位制を導入させてもらっている」{f801}{f802}「二種類の魔物を倒した総数で{f801}順位を決定するんだ。{f801}他のギルドに負けぬよう、頑張ってね」{f801}{f802}{f804}{0500}「それと一度でもこのフロアから出るか{f801}{f804}{0600}アリアドネの糸{f804}{0000}などで街に戻ったら{f801}その時点で集計が始まり大会は終了だ」{f801}{f804}{0000}{f802}「そのときに討伐数が10体未満だった{f801}場合はクエスト失敗となるので要注意だ」{f801}{f802}「クエストを終えたら、{f801}冒険者ギルドに赴き、ギルド長に{f801}君たちの順位を聞くといい」{f801}{f802}「説明は以上だが何か質問はある?{f801}…なければ、今回の討伐大会を{f801}始めさせてもらうよ」{f801}</target>
  </entry>
  <entry id="33">
    <source>{f804}{0500}討伐大会を始めますか?{f804}{0000}{f801}始める{f801}説明を聞く{f801}やっぱりやめる{f801}</source>
    <target>{f804}{0500}討伐大会を始めますか?{f804}{0000}{f801}始める{f801}説明を聞く{f801}やっぱりやめる{f801}</target>
  </entry>
  <entry id="34">
    <source>「…意気込みは十分なようだね。{f801}では、行きたまえ!{f801}{f840}よ!」{f801}</source>
    <target>「…意気込みは十分なようだね。{f801}では、行きたまえ!{f801}{f840}よ!」{f801}</target>
  </entry>
  <entry id="35">
    <source>兵士からの激励を受けた君たちは{f801}指定された魔物を探すべく、意気揚々と{f801}迷宮の奥へ歩みを進めていく…。{f801}</source>
    <target>兵士からの激励を受けた君たちは{f801}指定された魔物を探すべく、意気揚々と{f801}迷宮の奥へ歩みを進めていく…。{f801}</target>
  </entry>
  <entry id="36">
    <source>「このクエストは厳しい戦いになる…。{f801}準備は十分に整えてくることだね。{f801}準備が整ったら、また声をかけてくれ」{f801}</source>
    <target>「このクエストは厳しい戦いになる…。{f801}準備は十分に整えてくることだね。{f801}準備が整ったら、また声をかけてくれ」{f801}</target>
  </entry>
  <entry id="38">
    <source>「準備は整えてきたかい?{f801}問題がなければ、今回の討伐大会を{f801}始めさせてもらいたいのだが…」{f801}</source>
    <target>「準備は整えてきたかい?{f801}問題がなければ、今回の討伐大会を{f801}始めさせてもらいたいのだが…」{f801}</target>
  </entry>
  <entry id="40">
    <source>気球艇へ向かおうとする君たちの前に、{f801}一人の兵士が立ちはだかる。{f801}</source>
    <target>気球艇へ向かおうとする君たちの前に、{f801}一人の兵士が立ちはだかる。{f801}</target>
  </entry>
  <entry id="41">
    <source>「君たちは…{f840}だね?{f801}このまま外に出てしまうと、君たちの{f801}クエストはこの時点で終了だ」{f801}{f802}「もう、集計を始めても構わないというなら{f801}自由に行動しても構わない」{f801}</source>
    <target>「君たちは…{f840}だね?{f801}このまま外に出てしまうと、君たちの{f801}クエストはこの時点で終了だ」{f801}{f802}「もう、集計を始めても構わないというなら{f801}自由に行動しても構わない」{f801}</target>
  </entry>
  <entry id="42">
    <source>「君たちは…{f840}だな?{f801}君たちはまだ規定の討伐数である{f801}10体を満たしていないぞ」{f801}{f802}「このままこのフロアを出ると{f801}君たちのクエストは失敗と{f801}なってしまうので気をつけるんだ」{f801}</source>
    <target>「君たちは…{f840}だな?{f801}君たちはまだ規定の討伐数である{f801}10体を満たしていないぞ」{f801}{f802}「このままこのフロアを出ると{f801}君たちのクエストは失敗と{f801}なってしまうので気をつけるんだ」{f801}</target>
  </entry>
  <entry id="43">
    <source>兵士はそういうと、持ち場に戻り{f801}姿勢を休める。{f801}{f802}君たちはこのまま、このフロアを{f801}出てもいいし、クエストを続けるべく{f801}引き返してもいい。{f801}</source>
    <target>兵士はそういうと、持ち場に戻り{f801}姿勢を休める。{f801}{f802}君たちはこのまま、このフロアを{f801}出てもいいし、クエストを続けるべく{f801}引き返してもいい。{f801}</target>
  </entry>
  <entry id="44">
    <source>君たちは兵士の忠告を無視して{f801}迷宮から出てしまった!{f801}これではクエストは失敗だ!{f801}{f802}もう一度挑戦したいなら{f801}酒場に戻って依頼を破棄し{f801}再度受け直さなくてはならない。{f801}</source>
    <target>君たちは兵士の忠告を無視して{f801}迷宮から出てしまった!{f801}これではクエストは失敗だ!{f801}{f802}もう一度挑戦したいなら{f801}酒場に戻って依頼を破棄し{f801}再度受け直さなくてはならない。{f801}</target>
  </entry>
  <entry id="45">
    <source>討伐大会のクエストを終えた君たちは{f801}街の広場に戻ってくる。{f801}{f802}兵士の話によると、結果発表は{f801}冒険者ギルドで行われるはずだ。{f801}このまま、結果を見に行くといいだろう。{f801}</source>
    <target>討伐大会のクエストを終えた君たちは{f801}街の広場に戻ってくる。{f801}{f802}兵士の話によると、結果発表は{f801}冒険者ギルドで行われるはずだ。{f801}このまま、結果を見に行くといいだろう。{f801}</target>
  </entry>
  <entry id="50">
    <source>君たちは、10体目の魔物を{f801}倒したところで、剣を納め{f801}兵士の言葉を思い返す。{f801}{f802}その言葉によると、魔物を10体討伐{f801}することが依頼達成の{f801}最低条件だったはずだ。{f801}{f802}そして今、君たちはその条件を満たした!{f801}君たちは、このまま依頼を終えてもいいし{f801}上位を目指して戦い続けてもいい。{f801}</source>
    <target>君たちは、10体目の魔物を{f801}倒したところで、剣を納め{f801}兵士の言葉を思い返す。{f801}{f802}その言葉によると、魔物を10体討伐{f801}することが依頼達成の{f801}最低条件だったはずだ。{f801}{f802}そして今、君たちはその条件を満たした!{f801}君たちは、このまま依頼を終えてもいいし{f801}上位を目指して戦い続けてもいい。{f801}</target>
  </entry>
  <entry id="51">
    <source>上位入賞を目指し、戦い続けた君たちは{f801}かなりの数の魔物を倒した!{f801}これなら入賞できるかもしれない。{f801}{f802}しかし周囲からはちらほらと{f801}戦闘の音が聞こえてくる…。{f801}まだ戦っているギルドがいるようだ。{f801}{f802}君たちは現状に満足して依頼を{f801}終えてもいいし、{f801}上位を目指して戦い続けてもいい。{f801}</source>
    <target>上位入賞を目指し、戦い続けた君たちは{f801}かなりの数の魔物を倒した!{f801}これなら入賞できるかもしれない。{f801}{f802}しかし周囲からはちらほらと{f801}戦闘の音が聞こえてくる…。{f801}まだ戦っているギルドがいるようだ。{f801}{f802}君たちは現状に満足して依頼を{f801}終えてもいいし、{f801}上位を目指して戦い続けてもいい。{f801}</target>
  </entry>
  <entry id="52">
    <source>体力の配分に気を使い、戦い続けた{f801}君たちは、相当な数の魔物を倒した!{f801}これなら上位に食い込めるだろう!{f801}{f802}しかし、迷宮内には僅かに戦闘の気配が{f801}感じられる…どうやら、君たちの他にも{f801}優勝を目指すギルドがいるようだ。{f801}{f802}君たちは現状に満足して依頼を{f801}終えてもいいし、彼らに勝つべく{f801}更に戦い続けても構わない。{f801}</source>
    <target>体力の配分に気を使い、戦い続けた{f801}君たちは、相当な数の魔物を倒した!{f801}これなら上位に食い込めるだろう!{f801}{f802}しかし、迷宮内には僅かに戦闘の気配が{f801}感じられる…どうやら、君たちの他にも{f801}優勝を目指すギルドがいるようだ。{f801}{f802}君たちは現状に満足して依頼を{f801}終えてもいいし、彼らに勝つべく{f801}更に戦い続けても構わない。{f801}</target>
  </entry>
  <entry id="53">
    <source>優勝への想いを支えに戦い続けた{f801}君たちは、最早数えきれないほどの{f801}魔物を討伐した!{f801}{f802}今や、この迷宮で戦い続けているのは{f801}君たちだけのようだ!{f801}これなら優勝は揺らがないだろう!{f801}{f802}…おめでとう!{f801}後は、冒険者ギルドへ赴き、この輝かしい{f801}結果を報告すればいいだろう!{f801}</source>
    <target>優勝への想いを支えに戦い続けた{f801}君たちは、最早数えきれないほどの{f801}魔物を討伐した!{f801}{f802}今や、この迷宮で戦い続けているのは{f801}君たちだけのようだ!{f801}これなら優勝は揺らがないだろう!{f801}{f802}…おめでとう!{f801}後は、冒険者ギルドへ赴き、この輝かしい{f801}結果を報告すればいいだろう!{f801}</target>
  </entry>
  <entry id="60">
    <source>よし、全員帰ってきたようだな。{f801}では早速だが、今回の討伐大会の{f801}成績優秀者の発表を行わせてもらおう。{f801}{f802}まずは第三位!{f801}</source>
    <target>よし、全員帰ってきたようだな。{f801}では早速だが、今回の討伐大会の{f801}成績優秀者の発表を行わせてもらおう。{f801}{f802}まずは第三位!{f801}</target>
  </entry>
  <entry id="61">
    <source>お次は第二位!{f801}</source>
    <target>お次は第二位!{f801}</target>
  </entry>
  <entry id="62">
    <source>そして栄えある第一位は…。{f801}{f802}………。{f801}</source>
    <target>そして栄えある第一位は…。{f801}{f802}………。{f801}</target>
  </entry>
  <entry id="63">
    <source>………発表は以上だ!{f801}{f802}今回入賞した冒険者は、結果に驕らず{f801}そして入賞できなかった冒険者は{f801}己を磨き、高めるのだ。{f801}{f802}それでは解散!{f801}…お楽しみの副賞は、各自{f801}依頼を受けた酒場で受け取るように!{f801}</source>
    <target>………発表は以上だ!{f801}{f802}今回入賞した冒険者は、結果に驕らず{f801}そして入賞できなかった冒険者は{f801}己を磨き、高めるのだ。{f801}{f802}それでは解散!{f801}…お楽しみの副賞は、各自{f801}依頼を受けた酒場で受け取るように!{f801}</target>
  </entry>
  <entry id="65">
    <source>{f840}!{f801}{f804}{0500}{f810}{0100}体!{f804}{0000}{f801}おめでとう! 言うことなしだ!{f801}</source>
    <target>{f840}!{f801}{f804}{0500}{f810}{0100}体!{f804}{0000}{f801}おめでとう! 言うことなしだ!{f801}</target>
  </entry>
  <entry id="66">
    <source>{f840}!{f801}{f804}{0500}{f810}{0100}体!{f804}{0000}{f801}見事だ! 他の冒険者の規範たれ!{f801}</source>
    <target>{f840}!{f801}{f804}{0500}{f810}{0100}体!{f804}{0000}{f801}見事だ! 他の冒険者の規範たれ!{f801}</target>
  </entry>
  <entry id="67">
    <source>{f840}!{f801}{f804}{0500}{f810}{0100}体!{f804}{0000}{f801}どうした? 不調だったのか?{f801}</source>
    <target>{f840}!{f801}{f804}{0500}{f810}{0100}体!{f804}{0000}{f801}どうした? 不調だったのか?{f801}</target>
  </entry>
  <entry id="71">
    <source>ウルカヌス!{f801}{f804}{0500}{f810}{0100}体!{f804}{0000}{f801}火の後始末だけはしっかりな!{f801}</source>
    <target>ウルカヌス!{f801}{f804}{0500}{f810}{0100}体!{f804}{0000}{f801}火の後始末だけはしっかりな!{f801}</target>
  </entry>
  <entry id="72">
    <source>ハイブロウズ!{f801}{f804}{0500}{f810}{0100}体!{f804}{0000}{f801}一見に勝る百聞、見せてもらった!{f801}</source>
    <target>ハイブロウズ!{f801}{f804}{0500}{f810}{0100}体!{f804}{0000}{f801}一見に勝る百聞、見せてもらった!{f801}</target>
  </entry>
  <entry id="73">
    <source>美食探究者同盟!{f801}{f804}{0500}{f810}{0100}体!{f804}{0000}{f801}フォートレス5人とは恐れ入る!{f801}</source>
    <target>美食探究者同盟!{f801}{f804}{0500}{f810}{0100}体!{f804}{0000}{f801}フォートレス5人とは恐れ入る!{f801}</target>
  </entry>
  <entry id="74">
    <source>カーゴ第三整備班!{f801}{f804}{0500}{f810}{0100}体!{f804}{0000}{f801}本職の方も抜かるなよ!{f801}</source>
    <target>カーゴ第三整備班!{f801}{f804}{0500}{f810}{0100}体!{f804}{0000}{f801}本職の方も抜かるなよ!{f801}</target>
  </entry>
  <entry id="75">
    <source>ヤラカーナ!{f801}{f804}{0500}{f810}{0100}体!{f804}{0000}{f801}シャキっとしろ! シャキっと!{f801}</source>
    <target>ヤラカーナ!{f801}{f804}{0500}{f810}{0100}体!{f804}{0000}{f801}シャキっとしろ! シャキっと!{f801}</target>
  </entry>
  <entry id="80">
    <source>お前らか、どうやらワシが課した試練{f801}受けたようだな。{f801}{f802}タルシスの冒険者はつわもの揃いだ…{f801}入賞を果たしたいのなら{f801}それなりの覚悟が必要になる。{f801}{f802}よく、準備をしたら{f801}{f804}{0500}{f847}{f804}{0000}に行き{f801}説明を受けるがよい。{f801}</source>
    <target>お前らか、どうやらワシが課した試練{f801}受けたようだな。{f801}{f802}タルシスの冒険者はつわもの揃いだ…{f801}入賞を果たしたいのなら{f801}それなりの覚悟が必要になる。{f801}{f802}よく、準備をしたら{f801}{f804}{0500}{f847}{f804}{0000}に行き{f801}説明を受けるがよい。{f801}</target>
  </entry>
  <entry id="90">
    <source>現在{f810}{0000}ポイントです。ここでは、{f801}デバッグ用に汎用変数4・5番に指定した{f801}エンカウントIDと戦闘が行えます。{f801}</source>
    <target>現在{f810}{0000}ポイントです。ここでは、{f801}デバッグ用に汎用変数4・5番に指定した{f801}エンカウントIDと戦闘が行えます。{f801}</target>
  </entry>
  <entry id="91">
    <source>{f804}{0500}どうしますか?{f804}{0000}{f801}汎用変数4 ID{f810}{0200}{f801}汎用変数5 ID{f810}{0300}{f801}戦闘をしない{f801}</source>
    <target>{f804}{0500}どうしますか?{f804}{0000}{f801}汎用変数4 ID{f810}{0200}{f801}汎用変数5 ID{f810}{0300}{f801}戦闘をしない{f801}</target>
  </entry>
  <entry id="92">
    <source>直前の戦闘にて{f801}{f810}{0100}ポイントを入手。{f801}</source>
    <target>直前の戦闘にて{f801}{f810}{0100}ポイントを入手。{f801}</target>
  </entry>
  <entry id="93">
    <source>ダミー{f801}</source>
    <target>ダミー{f801}</target>
  </entry>
  <entry id="100">
    <source>詳しいルールは{f804}{0500}{f847}の{f810}{0200}階{f804}{0000}にいる{f801}兵士に聞いて頂戴。{f801}</source>
    <target>詳しいルールは{f804}{0500}{f847}の{f810}{0200}階{f804}{0000}にいる{f801}兵士に聞いて頂戴。{f801}</target>
  </entry>
  <entry id="101">
    <source>詳しいルールは{f804}{0500}{f847}{f804}{0000}にいる{f801}兵士に聞いて頂戴。{f801}</source>
    <target>詳しいルールは{f804}{0500}{f847}{f804}{0000}にいる{f801}兵士に聞いて頂戴。{f801}</target>
  </entry>
</mbm>
